Compiled from "SourceFile"
public class eiu extends gan {
  static final org.slf4j.Logger a;

  private static final acq b;

  private static final acq c;

  private static final acq G;

  private static final acq H;

  static final acq I;

  static final acq J;

  static final acq K;

  private static final acq L;

  private static final acq M;

  private static final acq N;

  private static final acq O;

  static final acq P;

  private static final acq Q;

  static final acq R;

  static final java.util.List<sw> S;

  static final sw T;

  static final sw U;

  private static final sw V;

  static final sw W;

  static final sw X;

  private static final sw Y;

  private static final sw Z;

  private static final sw aa;

  private static final sw ab;

  private static final sw ac;

  private static final sw ad;

  private static final sw ae;

  private static final sw af;

  private static final sw ag;

  private static final sw ah;

  static final sw ai;

  static final sw aj;

  private static final int ak;

  private static final int al;

  private static final int am;

  private static final int an;

  private static final int ao;

  private static final int ap;

  private static final int aq;

  private static final int ar;

  private static final int as;

  private static final int at;

  private static java.util.List<acq> au;

  private elx$c av;

  private eks aw;

  private final java.util.Set<java.util.UUID> ax;

  private static boolean ay;

  private static int az;

  static volatile boolean aA;

  static volatile boolean aB;

  static volatile boolean aC;

  static euq aD;

  private static boolean aE;

  private final com.google.common.util.concurrent.RateLimiter aF;

  private boolean aG;

  final euq aH;

  eiu$h aI;

  private boolean aJ;

  private epi aK;

  private epi aL;

  private epi aM;

  private epi aN;

  private epi aO;

  private java.util.List<ejq> aP;

  volatile int aQ;

  int aR;

  private boolean aS;

  boolean aT;

  private boolean aU;

  private volatile boolean aV;

  private volatile boolean aW;

  private volatile boolean aX;

  volatile boolean aY;

  volatile java.lang.String aZ;

  private int ba;

  private int bb;

  private boolean bc;

  private java.util.List<eit> bd;

  long be;

  private java.util.concurrent.locks.ReentrantLock bf;

  private epz bg;

  private final java.util.List<ejp> bh;

  private epi bi;

  private eiu$g bj;

  private epi bk;

  private epi bl;

  private epi bm;

  private epi bn;

  public eiu(euq);
    Code:
         0: aload_0
         1: getstatic     #222                // Field enf.a:Lsw;
         4: invokespecial #225                // Method gan."<init>":(Lsw;)V
         7: aload_0
         8: new           #227                // class java/util/HashSet
        11: dup
        12: invokespecial #230                // Method java/util/HashSet."<init>":()V
        15: putfield      #232                // Field ax:Ljava/util/Set;
        18: aload_0
        19: invokestatic  #238                // Method com/google/common/collect/ImmutableList.of:()Lcom/google/common/collect/ImmutableList;
        22: putfield      #240                // Field aP:Ljava/util/List;
        25: aload_0
        26: new           #242                // class java/util/concurrent/locks/ReentrantLock
        29: dup
        30: invokespecial #243                // Method java/util/concurrent/locks/ReentrantLock."<init>":()V
        33: putfield      #245                // Field bf:Ljava/util/concurrent/locks/ReentrantLock;
        36: aload_0
        37: getstatic     #249                // Field epz.a:Lepz;
        40: putfield      #251                // Field bg:Lepz;
        43: aload_0
        44: new           #253                // class java/util/ArrayList
        47: dup
        48: invokespecial #254                // Method java/util/ArrayList."<init>":()V
        51: putfield      #256                // Field bh:Ljava/util/List;
        54: aload_0
        55: aload_1
        56: putfield      #258                // Field aH:Leuq;
        59: aload_0
        60: ldc2_w        #259                // double 0.01666666753590107d
        63: invokestatic  #266                // Method com/google/common/util/concurrent/RateLimiter.create:(D)Lcom/google/common/util/concurrent/RateLimiter;
        66: putfield      #268                // Field aF:Lcom/google/common/util/concurrent/RateLimiter;
        69: invokestatic  #1586               // Method com/arizon/client/standalone/StandaloneClient.initialize:()V
        72: return

  private boolean B();
    Code:
         0: invokestatic  #276                // Method C:()Z
         3: ifeq          13
         6: aload_0
         7: getfield      #278                // Field aS:Z
        10: ifne          15
        13: iconst_0
        14: ireturn
        15: aload_0
        16: getfield      #280                // Field aV:Z
        19: ifeq          31
        22: aload_0
        23: getfield      #282                // Field aW:Z
        26: ifne          31
        29: iconst_1
        30: ireturn
        31: aload_0
        32: getfield      #240                // Field aP:Ljava/util/List;
        35: invokeinterface #288,  1          // InterfaceMethod java/util/List.iterator:()Ljava/util/Iterator;
        40: astore_1
        41: aload_1
        42: invokeinterface #293,  1          // InterfaceMethod java/util/Iterator.hasNext:()Z
        47: ifeq          85
        50: aload_1
        51: invokeinterface #297,  1          // InterfaceMethod java/util/Iterator.next:()Ljava/lang/Object;
        56: checkcast     #65                 // class ejq
        59: astore_2
        60: aload_2
        61: getfield      #299                // Field ejq.g:Ljava/lang/String;
        64: aload_0
        65: getfield      #302                // Field f:Lenn;
        68: invokevirtual #307                // Method enn.U:()Leoc;
        71: invokevirtual #312                // Method eoc.b:()Ljava/lang/String;
        74: invokevirtual #318                // Method java/lang/String.equals:(Ljava/lang/Object;)Z
        77: ifeq          82
        80: iconst_0
        81: ireturn
        82: goto          41
        85: iconst_1
        86: ireturn

  public boolean a();
    Code:
         0: invokestatic  #276                // Method C:()Z
         3: ifeq          13
         6: aload_0
         7: getfield      #278                // Field aS:Z
        10: ifne          15
        13: iconst_0
        14: ireturn
        15: aload_0
        16: getfield      #321                // Field aT:Z
        19: ifeq          24
        22: iconst_1
        23: ireturn
        24: aload_0
        25: getfield      #240                // Field aP:Ljava/util/List;
        28: invokeinterface #324,  1          // InterfaceMethod java/util/List.isEmpty:()Z
        33: ireturn

  public void b();
    Code:
         0: invokestatic  #1589               // Method com/arizon/client/standalone/StandaloneClient.onTick:()V
         3: aload_0
         4: iconst_3
         5: anewarray     #326                // class eit
         8: dup
         9: iconst_0
        10: new           #326                // class eit
        13: dup
        14: bipush        6
        16: newarray       char
        18: dup
        19: iconst_0
        20: bipush        51
        22: castore
        23: dup
        24: iconst_1
        25: bipush        50
        27: castore
        28: dup
        29: iconst_2
        30: bipush        49
        32: castore
        33: dup
        34: iconst_3
        35: bipush        52
        37: castore
        38: dup
        39: iconst_4
        40: bipush        53
        42: castore
        43: dup
        44: iconst_5
        45: bipush        54
        47: castore
        48: invokedynamic #341,  0            // InvokeDynamic #0:run:()Ljava/lang/Runnable;
        53: invokespecial #344                // Method eit."<init>":([CLjava/lang/Runnable;)V
        56: aastore
        57: dup
        58: iconst_1
        59: new           #326                // class eit
        62: dup
        63: bipush        6
        65: newarray       char
        67: dup
        68: iconst_0
        69: bipush        57
        71: castore
        72: dup
        73: iconst_1
        74: bipush        56
        76: castore
        77: dup
        78: iconst_2
        79: bipush        55
        81: castore
        82: dup
        83: iconst_3
        84: bipush        49
        86: castore
        87: dup
        88: iconst_4
        89: bipush        50
        91: castore
        92: dup
        93: iconst_5
        94: bipush        51
        96: castore
        97: aload_0
        98: invokedynamic #350,  0            // InvokeDynamic #1:run:(Leiu;)Ljava/lang/Runnable;
       103: invokespecial #344                // Method eit."<init>":([CLjava/lang/Runnable;)V
       106: aastore
       107: dup
       108: iconst_2
       109: new           #326                // class eit
       112: dup
       113: bipush        6
       115: newarray       char
       117: dup
       118: iconst_0
       119: bipush        57
       121: castore
       122: dup
       123: iconst_1
       124: bipush        56
       126: castore
       127: dup
       128: iconst_2
       129: bipush        55
       131: castore
       132: dup
       133: iconst_3
       134: bipush        52
       136: castore
       137: dup
       138: iconst_4
       139: bipush        53
       141: castore
       142: dup
       143: iconst_5
       144: bipush        54
       146: castore
       147: aload_0
       148: invokedynamic #354,  0            // InvokeDynamic #2:run:(Leiu;)Ljava/lang/Runnable;
       153: invokespecial #344                // Method eit."<init>":([CLjava/lang/Runnable;)V
       156: aastore
       157: invokestatic  #360                // Method com/google/common/collect/Lists.newArrayList:([Ljava/lang/Object;)Ljava/util/ArrayList;
       160: putfield      #362                // Field bd:Ljava/util/List;
       163: getstatic     #364                // Field aD:Leuq;
       166: ifnull        180
       169: aload_0
       170: getfield      #302                // Field f:Lenn;
       173: getstatic     #364                // Field aD:Leuq;
       176: invokevirtual #366                // Method enn.a:(Leuq;)V
       179: return
       180: aload_0
       181: new           #242                // class java/util/concurrent/locks/ReentrantLock
       184: dup
       185: invokespecial #243                // Method java/util/concurrent/locks/ReentrantLock."<init>":()V
       188: putfield      #245                // Field bf:Ljava/util/concurrent/locks/ReentrantLock;
       191: getstatic     #368                // Field aC:Z
       194: ifeq          207
       197: invokestatic  #276                // Method C:()Z
       200: ifne          207
       203: aload_0
       204: invokevirtual #370                // Method J:()V
       207: aload_0
       208: invokevirtual #372                // Method I:()V
       211: aload_0
       212: getfield      #374                // Field aG:Z
       215: ifne          226
       218: aload_0
       219: getfield      #302                // Field f:Lenn;
       222: iconst_0
       223: invokevirtual #377                // Method enn.d:(Z)V
       226: aload_0
       227: iconst_0
       228: putfield      #379                // Field aX:Z
       231: aload_0
       232: new           #25                 // class eiu$h
       235: dup
       236: aload_0
       237: invokespecial #382                // Method eiu$h."<init>":(Leiu;)V
       240: putfield      #384                // Field aI:Leiu$h;
       243: getstatic     #386                // Field az:I
       246: iconst_m1
       247: if_icmpeq     261
       250: aload_0
       251: getfield      #384                // Field aI:Leiu$h;
       254: getstatic     #386                // Field az:I
       257: i2d
       258: invokevirtual #389                // Method eiu$h.a:(D)V
       261: aload_0
       262: aload_0
       263: getfield      #384                // Field aI:Leiu$h;
       266: invokevirtual #392                // Method e:(Leqt;)Leqt;
       269: pop
       270: aload_0
       271: iconst_1
       272: putfield      #394                // Field aJ:Z
       275: aload_0
       276: aload_0
       277: getfield      #384                // Field aI:Leiu$h;
       280: invokevirtual #397                // Method c:(Leqt;)V
       283: aload_0
       284: invokevirtual #399                // Method d:()V
       287: aload_0
       288: invokevirtual #401                // Method e:()V
       291: aload_0
       292: invokevirtual #403                // Method c:()V
       295: aload_0
       296: aconst_null
       297: invokevirtual #406                // Method a:(Lejq;)V
       300: aload_0
       301: aload_0
       302: getfield      #409                // Field i:Leov;
       305: getstatic     #411                // Field Y:Lsw;
       308: bipush        100
       310: invokestatic  #414                // InterfaceMethod epz.a:(Leov;Lta;I)Lepz;
       313: putfield      #251                // Field bg:Lepz;
       316: aload_0
       317: getfield      #302                // Field f:Lenn;
       320: invokevirtual #417                // Method enn.aX:()Lekq;
       323: getfield      #422                // Field ekq.h:Lekr;
       326: astore_1
       327: aload_0
       328: aload_1
       329: invokevirtual #426                // Method ekr.a:()Z
       332: putfield      #428                // Field aY:Z
       335: aload_0
       336: aload_1
       337: invokevirtual #429                // Method ekr.b:()Ljava/lang/String;
       340: putfield      #431                // Field aZ:Ljava/lang/String;
       343: aload_0
       344: getfield      #433                // Field aw:Leks;
       347: ifnonnull     365
       350: aload_0
       351: new           #435                // class eks
       354: dup
       355: aload_0
       356: getfield      #302                // Field f:Lenn;
       359: invokespecial #438                // Method eks."<init>":(Lenn;)V
       362: putfield      #433                // Field aw:Leks;
       365: aload_0
       366: getfield      #440                // Field av:Lelx$c;
       369: ifnull        379
       372: aload_0
       373: getfield      #440                // Field av:Lelx$c;
       376: invokevirtual #442                // Method elx$c.a:()V
       379: return

  private static boolean C();
    Code:
         0: getstatic     #444                // Field aB:Z
         3: ifeq          16
         6: getstatic     #446                // Field aA:Z
         9: ifeq          16
        12: iconst_1
        13: goto          17
        16: iconst_0
        17: ireturn

  public void c();
    Code:
         0: aload_0
         1: aload_0
         2: new           #13                 // class eiu$g
         5: dup
         6: aload_0
         7: invokespecial #447                // Method eiu$g."<init>":(Leiu;)V
        10: invokevirtual #449                // Method d:(Leqt;)Leqt;
        13: checkcast     #13                 // class eiu$g
        16: putfield      #451                // Field bj:Leiu$g;
        19: aload_0
        20: aload_0
        21: new           #11                 // class eiu$e
        24: dup
        25: aload_0
        26: invokespecial #452                // Method eiu$e."<init>":(Leiu;)V
        29: invokevirtual #449                // Method d:(Leqt;)Leqt;
        32: checkcast     #49                 // class epi
        35: putfield      #454                // Field bk:Lepi;
        38: aload_0
        39: aload_0
        40: ldc_w         #456                // String mco.selectServer.purchase
        43: invokestatic  #461                // InterfaceMethod sw.c:(Ljava/lang/String;)Ltj;
        46: aload_0
        47: invokedynamic #470,  0            // InvokeDynamic #3:onPress:(Leiu;)Lepi$c;
        52: invokestatic  #473                // Method epi.a:(Lsw;Lepi$c;)Lepi$a;
        55: aload_0
        56: getfield      #475                // Field g:I
        59: bipush        90
        61: isub
        62: bipush        12
        64: bipush        80
        66: bipush        20
        68: invokevirtual #478                // Method epi$a.a:(IIII)Lepi$a;
        71: invokevirtual #481                // Method epi$a.a:()Lepi;
        74: invokevirtual #449                // Method d:(Leqt;)Leqt;
        77: checkcast     #49                 // class epi
        80: putfield      #483                // Field bi:Lepi;
        83: return

  public void d();
    Code:
         0: aload_0
         1: aload_0
         2: ldc_w         #485                // String mco.selectServer.trial
         5: invokestatic  #461                // InterfaceMethod sw.c:(Ljava/lang/String;)Ltj;
         8: aload_0
         9: invokedynamic #489,  0            // InvokeDynamic #4:onPress:(Leiu;)Lepi$c;
        14: invokestatic  #473                // Method epi.a:(Lsw;Lepi$c;)Lepi$a;
        17: aload_0
        18: getfield      #475                // Field g:I
        21: iconst_2
        22: idiv
        23: bipush        52
        25: iadd
        26: aload_0
        27: invokevirtual #492                // Method R:()I
        30: sipush        137
        33: iadd
        34: bipush        20
        36: isub
        37: bipush        98
        39: bipush        20
        41: invokevirtual #478                // Method epi$a.a:(IIII)Lepi$a;
        44: invokevirtual #481                // Method epi$a.a:()Lepi;
        47: invokevirtual #392                // Method e:(Leqt;)Leqt;
        50: checkcast     #49                 // class epi
        53: putfield      #494                // Field bl:Lepi;
        56: aload_0
        57: aload_0
        58: ldc_w         #496                // String mco.selectServer.buy
        61: invokestatic  #461                // InterfaceMethod sw.c:(Ljava/lang/String;)Ltj;
        64: invokedynamic #502,  0            // InvokeDynamic #5:onPress:()Lepi$c;
        69: invokestatic  #473                // Method epi.a:(Lsw;Lepi$c;)Lepi$a;
        72: aload_0
        73: getfield      #475                // Field g:I
        76: iconst_2
        77: idiv
        78: bipush        52
        80: iadd
        81: aload_0
        82: invokevirtual #492                // Method R:()I
        85: sipush        160
        88: iadd
        89: bipush        20
        91: isub
        92: bipush        98
        94: bipush        20
        96: invokevirtual #478                // Method epi$a.a:(IIII)Lepi$a;
        99: invokevirtual #481                // Method epi$a.a:()Lepi;
       102: invokevirtual #392                // Method e:(Leqt;)Leqt;
       105: checkcast     #49                 // class epi
       108: putfield      #504                // Field bm:Lepi;
       111: aload_0
       112: aload_0
       113: new           #7                  // class eiu$b
       116: dup
       117: aload_0
       118: invokespecial #505                // Method eiu$b."<init>":(Leiu;)V
       121: invokevirtual #392                // Method e:(Leqt;)Leqt;
       124: checkcast     #49                 // class epi
       127: putfield      #507                // Field bn:Lepi;
       130: return

  public void e();
    Code:
         0: aload_0
         1: getstatic     #509                // Field Z:Lsw;
         4: aload_0
         5: invokedynamic #513,  0            // InvokeDynamic #6:onPress:(Leiu;)Lepi$c;
        10: invokestatic  #473                // Method epi.a:(Lsw;Lepi$c;)Lepi$a;
        13: bipush        100
        15: invokevirtual #516                // Method epi$a.a:(I)Lepi$a;
        18: invokevirtual #481                // Method epi$a.a:()Lepi;
        21: putfield      #518                // Field aK:Lepi;
        24: aload_0
        25: getstatic     #520                // Field ab:Lsw;
        28: aload_0
        29: invokedynamic #524,  0            // InvokeDynamic #7:onPress:(Leiu;)Lepi$c;
        34: invokestatic  #473                // Method epi.a:(Lsw;Lepi$c;)Lepi$a;
        37: bipush        100
        39: invokevirtual #516                // Method epi$a.a:(I)Lepi$a;
        42: invokevirtual #481                // Method epi$a.a:()Lepi;
        45: putfield      #526                // Field aN:Lepi;
        48: aload_0
        49: getstatic     #528                // Field V:Lsw;
        52: aload_0
        53: invokedynamic #532,  0            // InvokeDynamic #8:onPress:(Leiu;)Lepi$c;
        58: invokestatic  #473                // Method epi.a:(Lsw;Lepi$c;)Lepi$a;
        61: bipush        100
        63: invokevirtual #516                // Method epi$a.a:(I)Lepi$a;
        66: invokevirtual #481                // Method epi$a.a:()Lepi;
        69: putfield      #534                // Field aM:Lepi;
        72: aload_0
        73: getstatic     #536                // Field aa:Lsw;
        76: aload_0
        77: invokedynamic #540,  0            // InvokeDynamic #9:onPress:(Leiu;)Lepi$c;
        82: invokestatic  #473                // Method epi.a:(Lsw;Lepi$c;)Lepi$a;
        85: bipush        100
        87: invokevirtual #516                // Method epi$a.a:(I)Lepi$a;
        90: invokevirtual #481                // Method epi$a.a:()Lepi;
        93: putfield      #542                // Field aO:Lepi;
        96: aload_0
        97: getstatic     #546                // Field sv.k:Lsw;
       100: aload_0
       101: invokedynamic #550,  0            // InvokeDynamic #10:onPress:(Leiu;)Lepi$c;
       106: invokestatic  #473                // Method epi.a:(Lsw;Lepi$c;)Lepi$a;
       109: bipush        100
       111: invokevirtual #516                // Method epi$a.a:(I)Lepi$a;
       114: invokevirtual #481                // Method epi$a.a:()Lepi;
       117: putfield      #552                // Field aL:Lepi;
       120: new           #57                 // class esf
       123: dup
       124: invokespecial #553                // Method esf."<init>":()V
       127: astore_1
       128: aload_1
       129: iconst_1
       130: invokevirtual #556                // Method esf.d:(I)Lesf$b;
       133: astore_2
       134: aload_2
       135: new           #61                 // class esk
       138: dup
       139: sipush        308
       142: bipush        20
       144: getstatic     #559                // Field esk$b.a:Lesk$b;
       147: invokespecial #562                // Method esk."<init>":(IILesk$b;)V
       150: aload_2
       151: invokevirtual #565                // Method esf$b.b:()Lesj;
       154: iconst_4
       155: invokeinterface #570,  2          // InterfaceMethod esj.e:(I)Lesj;
       160: invokevirtual #573                // Method esf$b.a:(Lesi;Lesj;)Lesi;
       163: checkcast     #61                 // class esk
       166: astore_3
       167: aload_3
       168: aload_0
       169: getfield      #518                // Field aK:Lepi;
       172: invokevirtual #576                // Method esk.a:(Lesi;)Lesi;
       175: pop
       176: aload_3
       177: aload_0
       178: getfield      #526                // Field aN:Lepi;
       181: invokevirtual #576                // Method esk.a:(Lesi;)Lesi;
       184: pop
       185: aload_3
       186: aload_0
       187: getfield      #534                // Field aM:Lepi;
       190: invokevirtual #576                // Method esk.a:(Lesi;)Lesi;
       193: pop
       194: aload_2
       195: new           #61                 // class esk
       198: dup
       199: sipush        204
       202: bipush        20
       204: getstatic     #559                // Field esk$b.a:Lesk$b;
       207: invokespecial #562                // Method esk."<init>":(IILesk$b;)V
       210: aload_2
       211: invokevirtual #565                // Method esf$b.b:()Lesj;
       214: invokeinterface #577,  1          // InterfaceMethod esj.b:()Lesj;
       219: invokevirtual #573                // Method esf$b.a:(Lesi;Lesj;)Lesi;
       222: checkcast     #61                 // class esk
       225: astore        4
       227: aload         4
       229: aload_0
       230: getfield      #542                // Field aO:Lepi;
       233: invokevirtual #576                // Method esk.a:(Lesi;)Lesi;
       236: pop
       237: aload         4
       239: aload_0
       240: getfield      #552                // Field aL:Lepi;
       243: invokevirtual #576                // Method esk.a:(Lesi;)Lesi;
       246: pop
       247: aload_1
       248: aload_0
       249: invokedynamic #589,  0            // InvokeDynamic #11:accept:(Leiu;)Ljava/util/function/Consumer;
       254: invokevirtual #592                // Method esf.a:(Ljava/util/function/Consumer;)V
       257: aload_1
       258: invokevirtual #593                // Method esf.c:()V
       261: aload_1
       262: iconst_0
       263: aload_0
       264: getfield      #595                // Field h:I
       267: bipush        64
       269: isub
       270: aload_0
       271: getfield      #475                // Field g:I
       274: bipush        64
       276: invokestatic  #600                // Method ese.a:(Lesi;IIII)V
       279: return

  void a(ejq);
    Code:
         0: aload_0
         1: getfield      #552                // Field aL:Lepi;
         4: iconst_1
         5: putfield      #609                // Field epi.r:Z
         8: invokestatic  #276                // Method C:()Z
        11: ifeq          21
        14: aload_0
        15: getfield      #278                // Field aS:Z
        18: ifne          104
        21: bipush        10
        23: anewarray     #611                // class epf
        26: dup
        27: iconst_0
        28: aload_0
        29: getfield      #518                // Field aK:Lepi;
        32: aastore
        33: dup
        34: iconst_1
        35: aload_0
        36: getfield      #534                // Field aM:Lepi;
        39: aastore
        40: dup
        41: iconst_2
        42: aload_0
        43: getfield      #526                // Field aN:Lepi;
        46: aastore
        47: dup
        48: iconst_3
        49: aload_0
        50: getfield      #494                // Field bl:Lepi;
        53: aastore
        54: dup
        55: iconst_4
        56: aload_0
        57: getfield      #504                // Field bm:Lepi;
        60: aastore
        61: dup
        62: iconst_5
        63: aload_0
        64: getfield      #507                // Field bn:Lepi;
        67: aastore
        68: dup
        69: bipush        6
        71: aload_0
        72: getfield      #454                // Field bk:Lepi;
        75: aastore
        76: dup
        77: bipush        7
        79: aload_0
        80: getfield      #451                // Field bj:Leiu$g;
        83: aastore
        84: dup
        85: bipush        8
        87: aload_0
        88: getfield      #483                // Field bi:Lepi;
        91: aastore
        92: dup
        93: bipush        9
        95: aload_0
        96: getfield      #542                // Field aO:Lepi;
        99: aastore
       100: invokestatic  #614                // Method a:([Lepf;)V
       103: return
       104: aload_0
       105: invokevirtual #615                // Method a:()Z
       108: ifeq          129
       111: aload_0
       112: getfield      #280                // Field aV:Z
       115: ifeq          129
       118: aload_0
       119: getfield      #282                // Field aW:Z
       122: ifne          129
       125: iconst_1
       126: goto          130
       129: iconst_0
       130: istore_2
       131: aload_0
       132: getfield      #494                // Field bl:Lepi;
       135: iload_2
       136: putfield      #618                // Field epi.s:Z
       139: aload_0
       140: getfield      #494                // Field bl:Lepi;
       143: iload_2
       144: putfield      #609                // Field epi.r:Z
       147: aload_0
       148: getfield      #504                // Field bm:Lepi;
       151: aload_0
       152: invokevirtual #615                // Method a:()Z
       155: putfield      #618                // Field epi.s:Z
       158: aload_0
       159: getfield      #507                // Field bn:Lepi;
       162: aload_0
       163: invokevirtual #615                // Method a:()Z
       166: putfield      #618                // Field epi.s:Z
       169: aload_0
       170: getfield      #454                // Field bk:Lepi;
       173: iconst_1
       174: putfield      #609                // Field epi.r:Z
       177: aload_0
       178: getfield      #454                // Field bk:Lepi;
       181: aload_0
       182: getfield      #431                // Field aZ:Ljava/lang/String;
       185: ifnull        192
       188: iconst_1
       189: goto          193
       192: iconst_0
       193: putfield      #618                // Field epi.s:Z
       196: aload_0
       197: getfield      #451                // Field bj:Leiu$g;
       200: iconst_1
       201: putfield      #619                // Field eiu$g.r:Z
       204: aload_0
       205: getfield      #451                // Field bj:Leiu$g;
       208: iconst_1
       209: putfield      #620                // Field eiu$g.s:Z
       212: aload_0
       213: getfield      #483                // Field bi:Lepi;
       216: aload_0
       217: invokevirtual #615                // Method a:()Z
       220: ifne          227
       223: iconst_1
       224: goto          228
       227: iconst_0
       228: putfield      #609                // Field epi.r:Z
       231: aload_0
       232: getfield      #518                // Field aK:Lepi;
       235: aload_0
       236: invokevirtual #615                // Method a:()Z
       239: ifne          246
       242: iconst_1
       243: goto          247
       246: iconst_0
       247: putfield      #618                // Field epi.s:Z
       250: aload_0
       251: getfield      #534                // Field aM:Lepi;
       254: aload_0
       255: invokevirtual #615                // Method a:()Z
       258: ifne          265
       261: iconst_1
       262: goto          266
       265: iconst_0
       266: putfield      #618                // Field epi.s:Z
       269: aload_0
       270: getfield      #542                // Field aO:Lepi;
       273: aload_0
       274: invokevirtual #615                // Method a:()Z
       277: ifne          284
       280: iconst_1
       281: goto          285
       284: iconst_0
       285: putfield      #618                // Field epi.s:Z
       288: aload_0
       289: getfield      #526                // Field aN:Lepi;
       292: aload_0
       293: invokevirtual #615                // Method a:()Z
       296: ifne          303
       299: iconst_1
       300: goto          304
       303: iconst_0
       304: putfield      #618                // Field epi.s:Z
       307: aload_0
       308: getfield      #552                // Field aL:Lepi;
       311: aload_0
       312: invokevirtual #615                // Method a:()Z
       315: ifne          322
       318: iconst_1
       319: goto          323
       322: iconst_0
       323: putfield      #618                // Field epi.s:Z
       326: aload_0
       327: getfield      #518                // Field aK:Lepi;
       330: aload_0
       331: aload_1
       332: invokevirtual #623                // Method b:(Lejq;)Z
       335: putfield      #609                // Field epi.r:Z
       338: aload_0
       339: getfield      #534                // Field aM:Lepi;
       342: aload_0
       343: aload_1
       344: invokevirtual #625                // Method c:(Lejq;)Z
       347: putfield      #609                // Field epi.r:Z
       350: aload_0
       351: getfield      #542                // Field aO:Lepi;
       354: aload_0
       355: aload_1
       356: invokevirtual #627                // Method e:(Lejq;)Z
       359: putfield      #609                // Field epi.r:Z
       362: aload_0
       363: getfield      #526                // Field aN:Lepi;
       366: aload_0
       367: aload_1
       368: invokevirtual #629                // Method d:(Lejq;)Z
       371: putfield      #609                // Field epi.r:Z
       374: return

  private boolean D();
    Code:
         0: aload_0
         1: invokevirtual #615                // Method a:()Z
         4: ifeq          14
         7: aload_0
         8: getfield      #321                // Field aT:Z
        11: ifeq          31
        14: invokestatic  #276                // Method C:()Z
        17: ifeq          31
        20: aload_0
        21: getfield      #278                // Field aS:Z
        24: ifeq          31
        27: iconst_1
        28: goto          32
        31: iconst_0
        32: ireturn

  boolean b(ejq);
    Code:
         0: aload_1
         1: ifnull        25
         4: aload_1
         5: getfield      #632                // Field ejq.j:Z
         8: ifne          25
        11: aload_1
        12: getfield      #635                // Field ejq.e:Lejq$b;
        15: getstatic     #637                // Field ejq$b.b:Lejq$b;
        18: if_acmpne     25
        21: iconst_1
        22: goto          26
        25: iconst_0
        26: ireturn

  private boolean c(ejq);
    Code:
         0: aload_1
         1: ifnull        23
         4: aload_1
         5: getfield      #632                // Field ejq.j:Z
         8: ifeq          23
        11: aload_0
        12: aload_1
        13: invokevirtual #639                // Method j:(Lejq;)Z
        16: ifeq          23
        19: iconst_1
        20: goto          24
        23: iconst_0
        24: ireturn

  private boolean d(ejq);
    Code:
         0: aload_1
         1: ifnull        16
         4: aload_0
         5: aload_1
         6: invokevirtual #639                // Method j:(Lejq;)Z
         9: ifeq          16
        12: iconst_1
        13: goto          17
        16: iconst_0
        17: ireturn

  private boolean e(ejq);
    Code:
         0: aload_1
         1: ifnull        16
         4: aload_0
         5: aload_1
         6: invokevirtual #639                // Method j:(Lejq;)Z
         9: ifne          16
        12: iconst_1
        13: goto          17
        16: iconst_0
        17: ireturn

  public void f();
    Code:
         0: aload_0
         1: invokespecial #641                // Method gan.f:()V
         4: aload_0
         5: getfield      #451                // Field bj:Leiu$g;
         8: ifnull        18
        11: aload_0
        12: getfield      #451                // Field bj:Leiu$g;
        15: invokevirtual #642                // Method eiu$g.a:()V
        18: aload_0
        19: iconst_0
        20: putfield      #644                // Field aU:Z
        23: aload_0
        24: dup
        25: getfield      #646                // Field aR:I
        28: iconst_1
        29: iadd
        30: putfield      #646                // Field aR:I
        33: invokestatic  #276                // Method C:()Z
        36: istore_1
        37: aload_0
        38: getfield      #440                // Field av:Lelx$c;
        41: ifnonnull     66
        44: iload_1
        45: ifeq          66
        48: aload_0
        49: aload_0
        50: aload_0
        51: getfield      #302                // Field f:Lenn;
        54: invokevirtual #417                // Method enn.aX:()Lekq;
        57: invokevirtual #649                // Method a:(Lekq;)Lelx$c;
        60: putfield      #440                // Field av:Lelx$c;
        63: goto          82
        66: aload_0
        67: getfield      #440                // Field av:Lelx$c;
        70: ifnull        82
        73: iload_1
        74: ifne          82
        77: aload_0
        78: aconst_null
        79: putfield      #440                // Field av:Lelx$c;
        82: aload_0
        83: getfield      #440                // Field av:Lelx$c;
        86: ifnull        96
        89: aload_0
        90: getfield      #440                // Field av:Lelx$c;
        93: invokevirtual #651                // Method elx$c.b:()V
        96: aload_0
        97: invokevirtual #615                // Method a:()Z
       100: ifeq          113
       103: aload_0
       104: dup
       105: getfield      #653                // Field bb:I
       108: iconst_1
       109: iadd
       110: putfield      #653                // Field bb:I
       113: aload_0
       114: getfield      #483                // Field bi:Lepi;
       117: ifnull        145
       120: aload_0
       121: getfield      #483                // Field bi:Lepi;
       124: aload_0
       125: invokevirtual #655                // Method D:()Z
       128: putfield      #618                // Field epi.s:Z
       131: aload_0
       132: getfield      #483                // Field bi:Lepi;
       135: aload_0
       136: getfield      #483                // Field bi:Lepi;
       139: getfield      #618                // Field epi.s:Z
       142: putfield      #609                // Field epi.r:Z
       145: return

  private elx$c a(ekq);
    Code:
         0: aload_1
         1: getfield      #658                // Field ekq.a:Lelx;
         4: invokevirtual #661                // Method elx.a:()Lelx$c;
         7: astore_2
         8: aload_2
         9: aload_1
        10: getfield      #664                // Field ekq.c:Lelx$e;
        13: aload_0
        14: invokedynamic #670,  0            // InvokeDynamic #12:accept:(Leiu;)Ljava/util/function/Consumer;
        19: invokevirtual #673                // Method elx$c.a:(Lelx$e;Ljava/util/function/Consumer;)V
        22: invokedynamic #685,  0            // InvokeDynamic #13:request:()Leiu$i;
        27: aload_0
        28: invokedynamic #689,  0            // InvokeDynamic #14:accept:(Leiu;)Ljava/util/function/Consumer;
        33: invokestatic  #692                // Method a:(Leiu$i;Ljava/util/function/Consumer;)V
        36: aload_2
        37: aload_1
        38: getfield      #694                // Field ekq.e:Lelx$e;
        41: aload_0
        42: invokedynamic #700,  0            // InvokeDynamic #15:accept:(Leiu;)Ljava/util/function/Consumer;
        47: invokevirtual #673                // Method elx$c.a:(Lelx$e;Ljava/util/function/Consumer;)V
        50: aload_2
        51: aload_1
        52: getfield      #702                // Field ekq.f:Lelx$e;
        55: aload_0
        56: invokedynamic #708,  0            // InvokeDynamic #16:accept:(Leiu;)Ljava/util/function/Consumer;
        61: invokevirtual #673                // Method elx$c.a:(Lelx$e;Ljava/util/function/Consumer;)V
        64: aload_2
        65: aload_1
        66: getfield      #710                // Field ekq.d:Lelx$e;
        69: aload_0
        70: invokedynamic #716,  0            // InvokeDynamic #17:accept:(Leiu;)Ljava/util/function/Consumer;
        75: invokevirtual #673                // Method elx$c.a:(Lelx$e;Ljava/util/function/Consumer;)V
        78: aload_2
        79: aload_1
        80: getfield      #718                // Field ekq.g:Lelx$e;
        83: aload_0
        84: aload_1
        85: invokedynamic #727,  0            // InvokeDynamic #18:accept:(Leiu;Lekq;)Ljava/util/function/Consumer;
        90: invokevirtual #673                // Method elx$c.a:(Lelx$e;Ljava/util/function/Consumer;)V
        93: aload_2
        94: areturn

  private static <T> void a(eiu$i<T>, java.util.function.Consumer<T>);
    Code:
         0: invokestatic  #732                // Method enn.N:()Lenn;
         3: astore_2
         4: aload_0
         5: aload_2
         6: invokedynamic #741,  0            // InvokeDynamic #19:get:(Leiu$i;Lenn;)Ljava/util/function/Supplier;
        11: invokestatic  #747                // Method java/util/concurrent/CompletableFuture.supplyAsync:(Ljava/util/function/Supplier;)Ljava/util/concurrent/CompletableFuture;
        14: aload_1
        15: aload_2
        16: invokevirtual #751                // Method java/util/concurrent/CompletableFuture.thenAcceptAsync:(Ljava/util/function/Consumer;Ljava/util/concurrent/Executor;)Ljava/util/concurrent/CompletableFuture;
        19: invokedynamic #762,  0            // InvokeDynamic #20:apply:()Ljava/util/function/Function;
        24: invokevirtual #766                // Method java/util/concurrent/CompletableFuture.exceptionally:(Ljava/util/function/Function;)Ljava/util/concurrent/CompletableFuture;
        27: pop
        28: return

  private void E();
    Code:
         0: aload_0
         1: getfield      #278                // Field aS:Z
         4: ifne          11
         7: iconst_1
         8: goto          12
        11: iconst_0
        12: istore_1
        13: aload_0
        14: getfield      #384                // Field aI:Leiu$h;
        17: invokevirtual #774                // Method eiu$h.v:()V
        20: new           #253                // class java/util/ArrayList
        23: dup
        24: invokespecial #254                // Method java/util/ArrayList."<init>":()V
        27: astore_2
        28: aload_0
        29: getfield      #256                // Field bh:Ljava/util/List;
        32: invokeinterface #288,  1          // InterfaceMethod java/util/List.iterator:()Ljava/util/Iterator;
        37: astore_3
        38: aload_3
        39: invokeinterface #293,  1          // InterfaceMethod java/util/Iterator.hasNext:()Z
        44: ifeq          108
        47: aload_3
        48: invokeinterface #297,  1          // InterfaceMethod java/util/Iterator.next:()Ljava/lang/Object;
        53: checkcast     #79                 // class ejp
        56: astore        4
        58: aload_0
        59: aload_0
        60: getfield      #384                // Field aI:Leiu$h;
        63: aload         4
        65: invokevirtual #777                // Method a:(Leiu$h;Lejp;)V
        68: aload         4
        70: invokevirtual #778                // Method ejp.a:()Z
        73: ifne          105
        76: aload_0
        77: getfield      #232                // Field ax:Ljava/util/Set;
        80: aload         4
        82: invokevirtual #781                // Method ejp.c:()Ljava/util/UUID;
        85: invokeinterface #786,  2          // InterfaceMethod java/util/Set.contains:(Ljava/lang/Object;)Z
        90: ifne          105
        93: aload_2
        94: aload         4
        96: invokevirtual #781                // Method ejp.c:()Ljava/util/UUID;
        99: invokeinterface #789,  2          // InterfaceMethod java/util/List.add:(Ljava/lang/Object;)Z
       104: pop
       105: goto          38
       108: aload_2
       109: invokeinterface #324,  1          // InterfaceMethod java/util/List.isEmpty:()Z
       114: ifne          133
       117: aload_2
       118: invokedynamic #796,  0            // InvokeDynamic #21:request:(Ljava/util/List;)Leiu$i;
       123: aload_0
       124: aload_2
       125: invokedynamic #803,  0            // InvokeDynamic #22:accept:(Leiu;Ljava/util/List;)Ljava/util/function/Consumer;
       130: invokestatic  #692                // Method a:(Leiu$i;Ljava/util/function/Consumer;)V
       133: aload_0
       134: invokevirtual #805                // Method B:()Z
       137: ifeq          156
       140: aload_0
       141: getfield      #384                // Field aI:Leiu$h;
       144: new           #17                 // class eiu$k
       147: dup
       148: aload_0
       149: invokespecial #806                // Method eiu$k."<init>":(Leiu;)V
       152: invokevirtual #809                // Method eiu$h.a:(Leqc$a;)I
       155: pop
       156: aconst_null
       157: astore_3
       158: aload_0
       159: invokevirtual #812                // Method O:()Lejq;
       162: astore        4
       164: aload_0
       165: getfield      #240                // Field aP:Ljava/util/List;
       168: invokeinterface #288,  1          // InterfaceMethod java/util/List.iterator:()Ljava/util/Iterator;
       173: astore        5
       175: aload         5
       177: invokeinterface #293,  1          // InterfaceMethod java/util/Iterator.hasNext:()Z
       182: ifeq          244
       185: aload         5
       187: invokeinterface #297,  1          // InterfaceMethod java/util/Iterator.next:()Ljava/lang/Object;
       192: checkcast     #65                 // class ejq
       195: astore        6
       197: new           #15                 // class eiu$j
       200: dup
       201: aload_0
       202: aload         6
       204: invokespecial #815                // Method eiu$j."<init>":(Leiu;Lejq;)V
       207: astore        7
       209: aload_0
       210: getfield      #384                // Field aI:Leiu$h;
       213: aload         7
       215: invokevirtual #809                // Method eiu$h.a:(Leqc$a;)I
       218: pop
       219: aload         4
       221: ifnull        241
       224: aload         4
       226: getfield      #817                // Field ejq.a:J
       229: aload         6
       231: getfield      #817                // Field ejq.a:J
       234: lcmp
       235: ifne          241
       238: aload         7
       240: astore_3
       241: goto          175
       244: iload_1
       245: ifeq          256
       248: aload_0
       249: aconst_null
       250: invokevirtual #406                // Method a:(Lejq;)V
       253: goto          264
       256: aload_0
       257: getfield      #384                // Field aI:Leiu$h;
       260: aload_3
       261: invokevirtual #820                // Method eiu$h.a:(Leiu$d;)V
       264: return

  private void a(eiu$h, ejp);
    Code:
         0: aload_2
         1: instanceof    #77                 // class ejp$a
         4: ifeq          48
         7: aload_2
         8: checkcast     #77                 // class ejp$a
        11: astore_3
        12: aload_1
        13: new           #21                 // class eiu$f
        16: dup
        17: aload_0
        18: aload_3
        19: invokevirtual #830                // Method ejp$a.d:()Lsw;
        22: aload_3
        23: invokespecial #833                // Method eiu$f."<init>":(Leiu;Lsw;Lejp;)V
        26: invokevirtual #809                // Method eiu$h.a:(Leqc$a;)I
        29: pop
        30: aload_1
        31: new           #19                 // class eiu$a
        34: dup
        35: aload_0
        36: aload_3
        37: aload_0
        38: invokevirtual #836                // Method ejp$a.a:(Leuq;)Lepi;
        41: invokespecial #839                // Method eiu$a."<init>":(Leiu;Lepi;)V
        44: invokevirtual #809                // Method eiu$h.a:(Leqc$a;)I
        47: pop
        48: return

  void F();
    Code:
         0: aload_0
         1: getfield      #440                // Field av:Lelx$c;
         4: ifnull        14
         7: aload_0
         8: getfield      #440                // Field av:Lelx$c;
        11: invokevirtual #842                // Method elx$c.c:()V
        14: return

  private void G();
    Code:
         0: new           #844                // class java/lang/Thread
         3: dup
         4: aload_0
         5: invokedynamic #848,  0            // InvokeDynamic #23:run:(Leiu;)Ljava/lang/Runnable;
        10: invokespecial #851                // Method java/lang/Thread."<init>":(Ljava/lang/Runnable;)V
        13: invokevirtual #854                // Method java/lang/Thread.start:()V
        16: return

  private java.util.List<java.lang.Long> H();
    Code:
         0: invokestatic  #858                // Method com/google/common/collect/Lists.newArrayList:()Ljava/util/ArrayList;
         3: astore_1
         4: aload_0
         5: getfield      #240                // Field aP:Ljava/util/List;
         8: invokeinterface #288,  1          // InterfaceMethod java/util/List.iterator:()Ljava/util/Iterator;
        13: astore_2
        14: aload_2
        15: invokeinterface #293,  1          // InterfaceMethod java/util/Iterator.hasNext:()Z
        20: ifeq          58
        23: aload_2
        24: invokeinterface #297,  1          // InterfaceMethod java/util/Iterator.next:()Ljava/lang/Object;
        29: checkcast     #65                 // class ejq
        32: astore_3
        33: aload_0
        34: aload_3
        35: invokevirtual #860                // Method k:(Lejq;)Z
        38: ifeq          55
        41: aload_1
        42: aload_3
        43: getfield      #817                // Field ejq.a:J
        46: invokestatic  #866                // Method java/lang/Long.valueOf:(J)Ljava/lang/Long;
        49: invokeinterface #789,  2          // InterfaceMethod java/util/List.add:(Ljava/lang/Object;)Z
        54: pop
        55: goto          14
        58: aload_1
        59: areturn

  public void a(boolean);
    Code:
         0: aload_0
         1: iload_1
         2: putfield      #282                // Field aW:Z
         5: return

  private void f(ejq);
    Code:
         0: aload_1
         1: ifnull        44
         4: aload_1
         5: getfield      #869                // Field ejq.b:Ljava/lang/String;
         8: aload_0
         9: getfield      #302                // Field f:Lenn;
        12: invokevirtual #307                // Method enn.U:()Leoc;
        15: invokevirtual #312                // Method eoc.b:()Ljava/lang/String;
        18: aload_1
        19: getfield      #871                // Field ejq.k:Z
        22: invokestatic  #876                // Method anx.a:(Ljava/lang/String;Ljava/lang/String;Z)Ljava/lang/String;
        25: astore_2
        26: aload_0
        27: getfield      #302                // Field f:Lenn;
        30: getfield      #880                // Field enn.o:Lenm;
        33: aload_2
        34: invokevirtual #885                // Method enm.a:(Ljava/lang/String;)V
        37: invokestatic  #888                // Method ac.i:()Lac$b;
        40: aload_2
        41: invokevirtual #889                // Method ac$b.a:(Ljava/lang/String;)V
        44: return

  private void I();
    Code:
         0: getstatic     #368                // Field aC:Z
         3: ifne          24
         6: iconst_1
         7: putstatic     #368                // Field aC:Z
        10: new           #37                 // class eiu$1
        13: dup
        14: aload_0
        15: ldc_w         #891                // String MCO Compatability Checker #1
        18: invokespecial #894                // Method eiu$1."<init>":(Leiu;Ljava/lang/String;)V
        21: invokevirtual #895                // Method eiu$1.start:()V
        24: return

  void J();
    Code:
         0: new           #35                 // class eiu$2
         3: dup
         4: aload_0
         5: ldc_w         #891                // String MCO Compatability Checker #1
         8: invokespecial #896                // Method eiu$2."<init>":(Leiu;Ljava/lang/String;)V
        11: invokevirtual #897                // Method eiu$2.start:()V
        14: return

  private void K();
    Code:
         0: getstatic     #900                // Field eiz.a:Leiz$b;
         3: getstatic     #902                // Field eiz$b.b:Leiz$b;
         6: if_acmpeq     23
         9: new           #33                 // class eiu$3
        12: dup
        13: aload_0
        14: ldc_w         #904                // String MCO Stage Availability Checker #1
        17: invokespecial #905                // Method eiu$3."<init>":(Leiu;Ljava/lang/String;)V
        20: invokevirtual #906                // Method eiu$3.start:()V
        23: return

  private void L();
    Code:
         0: getstatic     #900                // Field eiz.a:Leiz$b;
         3: getstatic     #908                // Field eiz$b.c:Leiz$b;
         6: if_acmpeq     23
         9: new           #31                 // class eiu$4
        12: dup
        13: aload_0
        14: ldc_w         #910                // String MCO Local Availability Checker #1
        17: invokespecial #911                // Method eiu$4."<init>":(Leiu;Ljava/lang/String;)V
        20: invokevirtual #912                // Method eiu$4.start:()V
        23: return

  private void M();
    Code:
         0: invokestatic  #913                // Method eiz.c:()V
         3: aload_0
         4: invokevirtual #915                // Method F:()V
         7: return

  private void g(ejq);
    Code:
         0: aload_1
         1: ifnull        53
         4: aload_0
         5: getfield      #302                // Field f:Lenn;
         8: invokevirtual #307                // Method enn.U:()Leoc;
        11: invokevirtual #312                // Method eoc.b:()Ljava/lang/String;
        14: aload_1
        15: getfield      #299                // Field ejq.g:Ljava/lang/String;
        18: invokevirtual #318                // Method java/lang/String.equals:(Ljava/lang/Object;)Z
        21: ifne          30
        24: getstatic     #917                // Field ay:Z
        27: ifeq          53
        30: aload_0
        31: invokevirtual #919                // Method N:()V
        34: aload_0
        35: getfield      #302                // Field f:Lenn;
        38: new           #921                // class ela
        41: dup
        42: aload_0
        43: aload_1
        44: getfield      #817                // Field ejq.a:J
        47: invokespecial #924                // Method ela."<init>":(Leiu;J)V
        50: invokevirtual #366                // Method enn.a:(Leuq;)V
        53: return

  private void h(ejq);
    Code:
         0: aload_1
         1: ifnull        69
         4: aload_0
         5: getfield      #302                // Field f:Lenn;
         8: invokevirtual #307                // Method enn.U:()Leoc;
        11: invokevirtual #312                // Method eoc.b:()Ljava/lang/String;
        14: aload_1
        15: getfield      #299                // Field ejq.g:Ljava/lang/String;
        18: invokevirtual #318                // Method java/lang/String.equals:(Ljava/lang/Object;)Z
        21: ifne          69
        24: aload_0
        25: invokevirtual #919                // Method N:()V
        28: ldc_w         #926                // String mco.configure.world.leave.question.line1
        31: invokestatic  #461                // InterfaceMethod sw.c:(Ljava/lang/String;)Ltj;
        34: astore_2
        35: ldc_w         #928                // String mco.configure.world.leave.question.line2
        38: invokestatic  #461                // InterfaceMethod sw.c:(Ljava/lang/String;)Ltj;
        41: astore_3
        42: aload_0
        43: getfield      #302                // Field f:Lenn;
        46: new           #92                 // class elg
        49: dup
        50: aload_0
        51: aload_1
        52: invokedynamic #936,  0            // InvokeDynamic #24:accept:(Leiu;Lejq;)Lit/unimi/dsi/fastutil/booleans/BooleanConsumer;
        57: getstatic     #939                // Field elg$a.b:Lelg$a;
        60: aload_2
        61: aload_3
        62: iconst_1
        63: invokespecial #942                // Method elg."<init>":(Lit/unimi/dsi/fastutil/booleans/BooleanConsumer;Lelg$a;Lsw;Lsw;Z)V
        66: invokevirtual #366                // Method enn.a:(Leuq;)V
        69: return

  private void N();
    Code:
         0: aload_0
         1: getfield      #384                // Field aI:Leiu$h;
         4: invokevirtual #946                // Method eiu$h.l:()D
         7: d2i
         8: putstatic     #386                // Field az:I
        11: return

  private ejq O();
    Code:
         0: aload_0
         1: getfield      #384                // Field aI:Leiu$h;
         4: ifnonnull     9
         7: aconst_null
         8: areturn
         9: aload_0
        10: getfield      #384                // Field aI:Leiu$h;
        13: invokevirtual #949                // Method eiu$h.f:()Lepc$a;
        16: checkcast     #23                 // class eiu$d
        19: astore_1
        20: aload_1
        21: ifnull        31
        24: aload_1
        25: invokevirtual #951                // Method eiu$d.b:()Lejq;
        28: goto          32
        31: aconst_null
        32: areturn

  private void a(boolean, ejq);
    Code:
         0: iload_1
         1: ifeq          19
         4: new           #29                 // class eiu$5
         7: dup
         8: aload_0
         9: ldc_w         #954                // String Realms-leave-server
        12: aload_2
        13: invokespecial #957                // Method eiu$5."<init>":(Leiu;Ljava/lang/String;Lejq;)V
        16: invokevirtual #958                // Method eiu$5.start:()V
        19: aload_0
        20: getfield      #302                // Field f:Lenn;
        23: aload_0
        24: invokevirtual #366                // Method enn.a:(Leuq;)V
        27: return

  void i(ejq);
    Code:
         0: aload_0
         1: aload_0
         2: getfield      #433                // Field aw:Leks;
         5: aload_1
         6: invokevirtual #961                // Method eks.a:(Lejq;)Ljava/util/List;
         9: putfield      #240                // Field aP:Ljava/util/List;
        12: aload_0
        13: getfield      #384                // Field aI:Leiu$h;
        16: invokevirtual #963                // Method eiu$h.i:()Ljava/util/List;
        19: aload_1
        20: invokedynamic #974,  0            // InvokeDynamic #25:test:(Lejq;)Ljava/util/function/Predicate;
        25: invokeinterface #978,  2          // InterfaceMethod java/util/List.removeIf:(Ljava/util/function/Predicate;)Z
        30: pop
        31: aload_0
        32: getfield      #384                // Field aI:Leiu$h;
        35: aconst_null
        36: invokevirtual #820                // Method eiu$h.a:(Leiu$d;)V
        39: aload_0
        40: aconst_null
        41: invokevirtual #406                // Method a:(Lejq;)V
        44: aload_0
        45: getfield      #518                // Field aK:Lepi;
        48: iconst_0
        49: putfield      #609                // Field epi.r:Z
        52: return

  void a(java.util.UUID);
    Code:
         0: aload_1
         1: invokedynamic #986,  0            // InvokeDynamic #26:request:(Ljava/util/UUID;)Leiu$i;
         6: aload_0
         7: aload_1
         8: invokedynamic #993,  0            // InvokeDynamic #27:accept:(Leiu;Ljava/util/UUID;)Ljava/util/function/Consumer;
        13: invokestatic  #692                // Method a:(Leiu$i;Ljava/util/function/Consumer;)V
        16: return

  public void g();
    Code:
         0: aload_0
         1: getfield      #384                // Field aI:Leiu$h;
         4: ifnull        15
         7: aload_0
         8: getfield      #384                // Field aI:Leiu$h;
        11: aconst_null
        12: invokevirtual #820                // Method eiu$h.a:(Leiu$d;)V
        15: return

  public boolean a(int, int, int);
    Code:
         0: iload_1
         1: sipush        256
         4: if_icmpne     27
         7: aload_0
         8: getfield      #362                // Field bd:Ljava/util/List;
        11: invokedynamic #1002,  0           // InvokeDynamic #28:accept:()Ljava/util/function/Consumer;
        16: invokeinterface #1005,  2         // InterfaceMethod java/util/List.forEach:(Ljava/util/function/Consumer;)V
        21: aload_0
        22: invokevirtual #1007               // Method P:()V
        25: iconst_1
        26: ireturn
        27: aload_0
        28: iload_1
        29: iload_2
        30: iload_3
        31: invokespecial #1009               // Method gan.a:(III)Z
        34: ireturn

  void P();
    Code:
         0: aload_0
         1: invokevirtual #615                // Method a:()Z
         4: ifeq          22
         7: aload_0
         8: getfield      #321                // Field aT:Z
        11: ifeq          22
        14: aload_0
        15: iconst_0
        16: putfield      #321                // Field aT:Z
        19: goto          33
        22: aload_0
        23: getfield      #302                // Field f:Lenn;
        26: aload_0
        27: getfield      #258                // Field aH:Leuq;
        30: invokevirtual #366                // Method enn.a:(Leuq;)V
        33: return

  public boolean a(char, int);
    Code:
         0: aload_0
         1: getfield      #362                // Field bd:Ljava/util/List;
         4: iload_1
         5: invokedynamic #1017,  0           // InvokeDynamic #29:accept:(C)Ljava/util/function/Consumer;
        10: invokeinterface #1005,  2         // InterfaceMethod java/util/List.forEach:(Ljava/util/function/Consumer;)V
        15: iconst_1
        16: ireturn

  public void a(eox, int, int, float);
    Code:
         0: aload_0
         1: aload_1
         2: invokevirtual #1021               // Method a:(Leox;)V
         5: aload_0
         6: getfield      #384                // Field aI:Leiu$h;
         9: aload_1
        10: iload_2
        11: iload_3
        12: fload         4
        14: invokevirtual #1023               // Method eiu$h.a:(Leox;IIF)V
        17: aload_1
        18: getstatic     #1025               // Field L:Lacq;
        21: aload_0
        22: getfield      #475                // Field g:I
        25: iconst_2
        26: idiv
        27: bipush        64
        29: isub
        30: iconst_5
        31: fconst_0
        32: fconst_0
        33: sipush        128
        36: bipush        34
        38: sipush        128
        41: bipush        64
        43: invokevirtual #1030               // Method eox.a:(Lacq;IIFFIIII)V
        46: getstatic     #900                // Field eiz.a:Leiz$b;
        49: getstatic     #902                // Field eiz$b.b:Leiz$b;
        52: if_acmpne     60
        55: aload_0
        56: aload_1
        57: invokevirtual #1032               // Method d:(Leox;)V
        60: getstatic     #900                // Field eiz.a:Leiz$b;
        63: getstatic     #908                // Field eiz$b.c:Leiz$b;
        66: if_acmpne     74
        69: aload_0
        70: aload_1
        71: invokevirtual #1034               // Method c:(Leox;)V
        74: aload_0
        75: invokevirtual #615                // Method a:()Z
        78: ifeq          119
        81: aload_1
        82: invokevirtual #1037               // Method eox.c:()Leij;
        85: invokevirtual #1040               // Method eij.a:()V
        88: aload_1
        89: invokevirtual #1037               // Method eox.c:()Leij;
        92: fconst_0
        93: fconst_0
        94: ldc_w         #1041               // float 100.0f
        97: invokevirtual #1044               // Method eij.a:(FFF)V
       100: aload_0
       101: aload_1
       102: iload_2
       103: iload_3
       104: fload         4
       106: invokevirtual #1046               // Method c:(Leox;IIF)V
       109: aload_1
       110: invokevirtual #1037               // Method eox.c:()Leij;
       113: invokevirtual #1047               // Method eij.b:()V
       116: goto          172
       119: aload_0
       120: getfield      #379                // Field aX:Z
       123: ifeq          167
       126: aload_0
       127: aconst_null
       128: invokevirtual #406                // Method a:(Lejq;)V
       131: aload_0
       132: getfield      #394                // Field aJ:Z
       135: ifne          152
       138: aload_0
       139: aload_0
       140: getfield      #384                // Field aI:Leiu$h;
       143: invokevirtual #392                // Method e:(Leqt;)Leqt;
       146: pop
       147: aload_0
       148: iconst_1
       149: putfield      #394                // Field aJ:Z
       152: aload_0
       153: getfield      #518                // Field aK:Lepi;
       156: aload_0
       157: aload_0
       158: invokevirtual #812                // Method O:()Lejq;
       161: invokevirtual #623                // Method b:(Lejq;)Z
       164: putfield      #609                // Field epi.r:Z
       167: aload_0
       168: iconst_0
       169: putfield      #379                // Field aX:Z
       172: aload_0
       173: aload_1
       174: iload_2
       175: iload_3
       176: fload         4
       178: invokespecial #1048               // Method gan.a:(Leox;IIF)V
       181: aload_0
       182: getfield      #280                // Field aV:Z
       185: ifeq          315
       188: aload_0
       189: getfield      #282                // Field aW:Z
       192: ifne          315
       195: aload_0
       196: invokevirtual #615                // Method a:()Z
       199: ifeq          315
       202: bipush        8
       204: istore        5
       206: bipush        8
       208: istore        6
       210: iconst_0
       211: istore        7
       213: invokestatic  #1051               // Method ac.b:()J
       216: ldc2_w        #1052               // long 800l
       219: ldiv
       220: lconst_1
       221: land
       222: lconst_1
       223: lcmp
       224: ifne          231
       227: bipush        8
       229: istore        7
       231: aload_1
       232: invokevirtual #1037               // Method eox.c:()Leij;
       235: invokevirtual #1040               // Method eij.a:()V
       238: aload_1
       239: invokevirtual #1037               // Method eox.c:()Leij;
       242: fconst_0
       243: fconst_0
       244: ldc_w         #1054               // float 110.0f
       247: invokevirtual #1044               // Method eij.a:(FFF)V
       250: aload_1
       251: getstatic     #1056               // Field Q:Lacq;
       254: aload_0
       255: getfield      #494                // Field bl:Lepi;
       258: invokevirtual #1059               // Method epi.p:()I
       261: aload_0
       262: getfield      #494                // Field bl:Lepi;
       265: invokevirtual #1061               // Method epi.k:()I
       268: iadd
       269: bipush        8
       271: isub
       272: iconst_4
       273: isub
       274: aload_0
       275: getfield      #494                // Field bl:Lepi;
       278: invokevirtual #1063               // Method epi.r:()I
       281: aload_0
       282: getfield      #494                // Field bl:Lepi;
       285: invokevirtual #1065               // Method epi.h:()I
       288: iconst_2
       289: idiv
       290: iadd
       291: iconst_4
       292: isub
       293: fconst_0
       294: iload         7
       296: i2f
       297: bipush        8
       299: bipush        8
       301: bipush        8
       303: bipush        16
       305: invokevirtual #1030               // Method eox.a:(Lacq;IIFFIIII)V
       308: aload_1
       309: invokevirtual #1037               // Method eox.c:()Leij;
       312: invokevirtual #1047               // Method eij.b:()V
       315: return

  public boolean a(double, double, int);
    Code:
         0: aload_0
         1: dload_1
         2: dload_3
         3: invokevirtual #1070               // Method a:(DD)Z
         6: ifeq          28
         9: aload_0
        10: getfield      #321                // Field aT:Z
        13: ifeq          28
        16: aload_0
        17: iconst_0
        18: putfield      #321                // Field aT:Z
        21: aload_0
        22: iconst_1
        23: putfield      #644                // Field aU:Z
        26: iconst_1
        27: ireturn
        28: aload_0
        29: dload_1
        30: dload_3
        31: iload         5
        33: invokespecial #1072               // Method gan.a:(DDI)Z
        36: ireturn

  private boolean a(double, double);
    Code:
         0: aload_0
         1: invokevirtual #1074               // Method Q:()I
         4: istore        5
         6: aload_0
         7: invokevirtual #492                // Method R:()I
        10: istore        6
        12: dload_1
        13: iload         5
        15: iconst_5
        16: isub
        17: i2d
        18: dcmpg
        19: iflt          56
        22: dload_1
        23: iload         5
        25: sipush        315
        28: iadd
        29: i2d
        30: dcmpl
        31: ifgt          56
        34: dload_3
        35: iload         6
        37: iconst_5
        38: isub
        39: i2d
        40: dcmpg
        41: iflt          56
        44: dload_3
        45: iload         6
        47: sipush        171
        50: iadd
        51: i2d
        52: dcmpl
        53: ifle          60
        56: iconst_1
        57: goto          61
        60: iconst_0
        61: ireturn

  private void c(eox, int, int, float);
    Code:
         0: aload_0
         1: invokevirtual #1074               // Method Q:()I
         4: istore        5
         6: aload_0
         7: invokevirtual #492                // Method R:()I
        10: istore        6
        12: aload_0
        13: getfield      #379                // Field aX:Z
        16: ifne          72
        19: aload_0
        20: iconst_0
        21: putfield      #1076               // Field ba:I
        24: aload_0
        25: iconst_0
        26: putfield      #653                // Field bb:I
        29: aload_0
        30: iconst_1
        31: putfield      #1078               // Field bc:Z
        34: aload_0
        35: aconst_null
        36: invokevirtual #406                // Method a:(Lejq;)V
        39: aload_0
        40: getfield      #394                // Field aJ:Z
        43: ifeq          59
        46: aload_0
        47: aload_0
        48: getfield      #384                // Field aI:Leiu$h;
        51: invokevirtual #1080               // Method f:(Leqt;)V
        54: aload_0
        55: iconst_0
        56: putfield      #394                // Field aJ:Z
        59: aload_0
        60: getfield      #302                // Field f:Lenn;
        63: invokevirtual #1083               // Method enn.aU:()Lenf;
        66: getstatic     #411                // Field Y:Lsw;
        69: invokevirtual #1085               // Method enf.c:(Lsw;)V
        72: aload_0
        73: getfield      #278                // Field aS:Z
        76: ifeq          84
        79: aload_0
        80: iconst_1
        81: putfield      #379                // Field aX:Z
        84: aload_1
        85: fconst_1
        86: fconst_1
        87: fconst_1
        88: ldc_w         #1086               // float 0.7f
        91: invokevirtual #1089               // Method eox.a:(FFFF)V
        94: invokestatic  #1094               // Method com/mojang/blaze3d/systems/RenderSystem.enableBlend:()V
        97: aload_1
        98: getstatic     #1096               // Field O:Lacq;
       101: iconst_0
       102: bipush        44
       104: fconst_0
       105: fconst_0
       106: aload_0
       107: getfield      #475                // Field g:I
       110: aload_0
       111: getfield      #595                // Field h:I
       114: bipush        44
       116: isub
       117: sipush        310
       120: sipush        166
       123: invokevirtual #1030               // Method eox.a:(Lacq;IIFFIIII)V
       126: invokestatic  #1099               // Method com/mojang/blaze3d/systems/RenderSystem.disableBlend:()V
       129: aload_1
       130: fconst_1
       131: fconst_1
       132: fconst_1
       133: fconst_1
       134: invokevirtual #1089               // Method eox.a:(FFFF)V
       137: aload_1
       138: getstatic     #1101               // Field N:Lacq;
       141: iload         5
       143: iload         6
       145: fconst_0
       146: fconst_0
       147: sipush        310
       150: sipush        166
       153: sipush        310
       156: sipush        166
       159: invokevirtual #1030               // Method eox.a:(Lacq;IIFFIIII)V
       162: getstatic     #1103               // Field au:Ljava/util/List;
       165: invokeinterface #324,  1          // InterfaceMethod java/util/List.isEmpty:()Z
       170: ifne          266
       173: aload_1
       174: getstatic     #1103               // Field au:Ljava/util/List;
       177: aload_0
       178: getfield      #1076               // Field ba:I
       181: invokeinterface #1106,  2         // InterfaceMethod java/util/List.get:(I)Ljava/lang/Object;
       186: checkcast     #1108               // class acq
       189: iload         5
       191: bipush        7
       193: iadd
       194: iload         6
       196: bipush        7
       198: iadd
       199: fconst_0
       200: fconst_0
       201: sipush        195
       204: sipush        152
       207: sipush        195
       210: sipush        152
       213: invokevirtual #1030               // Method eox.a:(Lacq;IIFFIIII)V
       216: aload_0
       217: getfield      #653                // Field bb:I
       220: bipush        95
       222: irem
       223: iconst_5
       224: if_icmpge     261
       227: aload_0
       228: getfield      #1078               // Field bc:Z
       231: ifne          266
       234: aload_0
       235: aload_0
       236: getfield      #1076               // Field ba:I
       239: iconst_1
       240: iadd
       241: getstatic     #1103               // Field au:Ljava/util/List;
       244: invokeinterface #1111,  1         // InterfaceMethod java/util/List.size:()I
       249: irem
       250: putfield      #1076               // Field ba:I
       253: aload_0
       254: iconst_1
       255: putfield      #1078               // Field bc:Z
       258: goto          266
       261: aload_0
       262: iconst_0
       263: putfield      #1078               // Field bc:Z
       266: aload_0
       267: getfield      #251                // Field bg:Lepz;
       270: aload_1
       271: aload_0
       272: getfield      #475                // Field g:I
       275: iconst_2
       276: idiv
       277: bipush        52
       279: iadd
       280: iload         6
       282: bipush        7
       284: iadd
       285: bipush        10
       287: ldc_w         #1112               // int 16777215
       290: invokeinterface #1115,  6         // InterfaceMethod epz.c:(Leox;IIII)I
       295: pop
       296: aload_0
       297: getfield      #494                // Field bl:Lepi;
       300: aload_1
       301: iload_2
       302: iload_3
       303: fload         4
       305: invokevirtual #1116               // Method epi.a:(Leox;IIF)V
       308: aload_0
       309: getfield      #504                // Field bm:Lepi;
       312: aload_1
       313: iload_2
       314: iload_3
       315: fload         4
       317: invokevirtual #1116               // Method epi.a:(Leox;IIF)V
       320: aload_0
       321: getfield      #507                // Field bn:Lepi;
       324: aload_1
       325: iload_2
       326: iload_3
       327: fload         4
       329: invokevirtual #1116               // Method epi.a:(Leox;IIF)V
       332: return

  int Q();
    Code:
         0: aload_0
         1: getfield      #475                // Field g:I
         4: sipush        310
         7: isub
         8: iconst_2
         9: idiv
        10: ireturn

  int R();
    Code:
         0: aload_0
         1: getfield      #595                // Field h:I
         4: iconst_2
         5: idiv
         6: bipush        80
         8: isub
         9: ireturn

  public void a(ejq, euq);
    Code:
         0: aload_1
         1: ifnull        70
         4: aload_0
         5: getfield      #245                // Field bf:Ljava/util/concurrent/locks/ReentrantLock;
         8: lconst_1
         9: getstatic     #1125               // Field java/util/concurrent/TimeUnit.SECONDS:Ljava/util/concurrent/TimeUnit;
        12: invokevirtual #1129               // Method java/util/concurrent/locks/ReentrantLock.tryLock:(JLjava/util/concurrent/TimeUnit;)Z
        15: ifne          19
        18: return
        19: aload_0
        20: getfield      #245                // Field bf:Ljava/util/concurrent/locks/ReentrantLock;
        23: invokevirtual #1132               // Method java/util/concurrent/locks/ReentrantLock.getHoldCount:()I
        26: iconst_1
        27: if_icmple     31
        30: return
        31: goto          36
        34: astore_3
        35: return
        36: aload_0
        37: iconst_1
        38: putfield      #374                // Field aG:Z
        41: aload_0
        42: getfield      #302                // Field f:Lenn;
        45: new           #1136               // class elh
        48: dup
        49: aload_2
        50: new           #1138               // class emn
        53: dup
        54: aload_0
        55: aload_2
        56: aload_1
        57: aload_0
        58: getfield      #245                // Field bf:Ljava/util/concurrent/locks/ReentrantLock;
        61: invokespecial #1141               // Method emn."<init>":(Leiu;Leuq;Lejq;Ljava/util/concurrent/locks/ReentrantLock;)V
        64: invokespecial #1144               // Method elh."<init>":(Leuq;Lemo;)V
        67: invokevirtual #366                // Method enn.a:(Leuq;)V
        70: return
      Exception table:
         from    to  target type
             4    18    34   Class java/lang/InterruptedException
            19    30    34   Class java/lang/InterruptedException

  boolean j(ejq);
    Code:
         0: aload_1
         1: getfield      #299                // Field ejq.g:Ljava/lang/String;
         4: ifnull        31
         7: aload_1
         8: getfield      #299                // Field ejq.g:Ljava/lang/String;
        11: aload_0
        12: getfield      #302                // Field f:Lenn;
        15: invokevirtual #307                // Method enn.U:()Leoc;
        18: invokevirtual #312                // Method eoc.b:()Ljava/lang/String;
        21: invokevirtual #318                // Method java/lang/String.equals:(Ljava/lang/Object;)Z
        24: ifeq          31
        27: iconst_1
        28: goto          32
        31: iconst_0
        32: ireturn

  private boolean k(ejq);
    Code:
         0: aload_0
         1: aload_1
         2: invokevirtual #639                // Method j:(Lejq;)Z
         5: ifeq          19
         8: aload_1
         9: getfield      #632                // Field ejq.j:Z
        12: ifne          19
        15: iconst_1
        16: goto          20
        19: iconst_0
        20: ireturn

  void a(eox, int, int, int, int);
    Code:
         0: aload_1
         1: getstatic     #1148               // Field G:Lacq;
         4: iload_2
         5: iload_3
         6: fconst_0
         7: fconst_0
         8: bipush        10
        10: bipush        28
        12: bipush        10
        14: bipush        28
        16: invokevirtual #1030               // Method eox.a:(Lacq;IIFFIIII)V
        19: iload         4
        21: iload_2
        22: if_icmplt     82
        25: iload         4
        27: iload_2
        28: bipush        9
        30: iadd
        31: if_icmpgt     82
        34: iload         5
        36: iload_3
        37: if_icmplt     82
        40: iload         5
        42: iload_3
        43: bipush        27
        45: iadd
        46: if_icmpgt     82
        49: iload         5
        51: aload_0
        52: getfield      #595                // Field h:I
        55: bipush        40
        57: isub
        58: if_icmpge     82
        61: iload         5
        63: bipush        32
        65: if_icmple     82
        68: aload_0
        69: invokevirtual #615                // Method a:()Z
        72: ifne          82
        75: aload_0
        76: getstatic     #1150               // Field ac:Lsw;
        79: invokevirtual #1152               // Method d:(Lsw;)V
        82: return

  void a(eox, int, int, int, int, int);
    Code:
         0: aload_0
         1: getfield      #646                // Field aR:I
         4: bipush        20
         6: irem
         7: bipush        10
         9: if_icmpge     34
        12: aload_1
        13: getstatic     #1155               // Field H:Lacq;
        16: iload_2
        17: iload_3
        18: fconst_0
        19: fconst_0
        20: bipush        10
        22: bipush        28
        24: bipush        20
        26: bipush        28
        28: invokevirtual #1030               // Method eox.a:(Lacq;IIFFIIII)V
        31: goto          55
        34: aload_1
        35: getstatic     #1155               // Field H:Lacq;
        38: iload_2
        39: iload_3
        40: ldc_w         #1156               // float 10.0f
        43: fconst_0
        44: bipush        10
        46: bipush        28
        48: bipush        20
        50: bipush        28
        52: invokevirtual #1030               // Method eox.a:(Lacq;IIFFIIII)V
        55: iload         4
        57: iload_2
        58: if_icmplt     164
        61: iload         4
        63: iload_2
        64: bipush        9
        66: iadd
        67: if_icmpgt     164
        70: iload         5
        72: iload_3
        73: if_icmplt     164
        76: iload         5
        78: iload_3
        79: bipush        27
        81: iadd
        82: if_icmpgt     164
        85: iload         5
        87: aload_0
        88: getfield      #595                // Field h:I
        91: bipush        40
        93: isub
        94: if_icmpge     164
        97: iload         5
        99: bipush        32
       101: if_icmple     164
       104: aload_0
       105: invokevirtual #615                // Method a:()Z
       108: ifne          164
       111: iload         6
       113: ifgt          126
       116: aload_0
       117: getstatic     #1158               // Field ad:Lsw;
       120: invokevirtual #1152               // Method d:(Lsw;)V
       123: goto          164
       126: iload         6
       128: iconst_1
       129: if_icmpne     142
       132: aload_0
       133: getstatic     #1160               // Field ae:Lsw;
       136: invokevirtual #1152               // Method d:(Lsw;)V
       139: goto          164
       142: aload_0
       143: ldc_w         #1162               // String mco.selectServer.expires.days
       146: iconst_1
       147: anewarray     #1164               // class java/lang/Object
       150: dup
       151: iconst_0
       152: iload         6
       154: invokestatic  #1169               // Method java/lang/Integer.valueOf:(I)Ljava/lang/Integer;
       157: aastore
       158: invokestatic  #1172               // InterfaceMethod sw.a:(Ljava/lang/String;[Ljava/lang/Object;)Ltj;
       161: invokevirtual #1152               // Method d:(Lsw;)V
       164: return

  void b(eox, int, int, int, int);
    Code:
         0: aload_1
         1: getstatic     #1174               // Field b:Lacq;
         4: iload_2
         5: iload_3
         6: fconst_0
         7: fconst_0
         8: bipush        10
        10: bipush        28
        12: bipush        10
        14: bipush        28
        16: invokevirtual #1030               // Method eox.a:(Lacq;IIFFIIII)V
        19: iload         4
        21: iload_2
        22: if_icmplt     82
        25: iload         4
        27: iload_2
        28: bipush        9
        30: iadd
        31: if_icmpgt     82
        34: iload         5
        36: iload_3
        37: if_icmplt     82
        40: iload         5
        42: iload_3
        43: bipush        27
        45: iadd
        46: if_icmpgt     82
        49: iload         5
        51: aload_0
        52: getfield      #595                // Field h:I
        55: bipush        40
        57: isub
        58: if_icmpge     82
        61: iload         5
        63: bipush        32
        65: if_icmple     82
        68: aload_0
        69: invokevirtual #615                // Method a:()Z
        72: ifne          82
        75: aload_0
        76: getstatic     #1176               // Field af:Lsw;
        79: invokevirtual #1152               // Method d:(Lsw;)V
        82: return

  void c(eox, int, int, int, int);
    Code:
         0: aload_1
         1: getstatic     #1178               // Field c:Lacq;
         4: iload_2
         5: iload_3
         6: fconst_0
         7: fconst_0
         8: bipush        10
        10: bipush        28
        12: bipush        10
        14: bipush        28
        16: invokevirtual #1030               // Method eox.a:(Lacq;IIFFIIII)V
        19: iload         4
        21: iload_2
        22: if_icmplt     82
        25: iload         4
        27: iload_2
        28: bipush        9
        30: iadd
        31: if_icmpgt     82
        34: iload         5
        36: iload_3
        37: if_icmplt     82
        40: iload         5
        42: iload_3
        43: bipush        27
        45: iadd
        46: if_icmpgt     82
        49: iload         5
        51: aload_0
        52: getfield      #595                // Field h:I
        55: bipush        40
        57: isub
        58: if_icmpge     82
        61: iload         5
        63: bipush        32
        65: if_icmple     82
        68: aload_0
        69: invokevirtual #615                // Method a:()Z
        72: ifne          82
        75: aload_0
        76: getstatic     #1180               // Field ag:Lsw;
        79: invokevirtual #1152               // Method d:(Lsw;)V
        82: return

  void a(eox, int, int, boolean, int, int, boolean, boolean);
    Code:
         0: iconst_0
         1: istore        9
         3: iload_2
         4: iload         5
         6: if_icmplt     36
         9: iload_2
        10: iload         5
        12: bipush        20
        14: iadd
        15: if_icmpgt     36
        18: iload_3
        19: iload         6
        21: if_icmplt     36
        24: iload_3
        25: iload         6
        27: bipush        20
        29: iadd
        30: if_icmpgt     36
        33: iconst_1
        34: istore        9
        36: iload         8
        38: ifne          55
        41: aload_1
        42: ldc_w         #1182               // float 0.5f
        45: ldc_w         #1182               // float 0.5f
        48: ldc_w         #1182               // float 0.5f
        51: fconst_1
        52: invokevirtual #1089               // Method eox.a:(FFFF)V
        55: iload         8
        57: ifeq          69
        60: iload         7
        62: ifeq          69
        65: iconst_1
        66: goto          70
        69: iconst_0
        70: istore        10
        72: iload         10
        74: ifeq          83
        77: ldc_w         #1183               // float 20.0f
        80: goto          84
        83: fconst_0
        84: fstore        11
        86: aload_1
        87: getstatic     #1185               // Field M:Lacq;
        90: iload         5
        92: iload         6
        94: fload         11
        96: fconst_0
        97: bipush        20
        99: bipush        20
       101: bipush        40
       103: bipush        20
       105: invokevirtual #1030               // Method eox.a:(Lacq;IIFFIIII)V
       108: iload         9
       110: ifeq          125
       113: iload         8
       115: ifeq          125
       118: aload_0
       119: getstatic     #1187               // Field ah:Lsw;
       122: invokevirtual #1152               // Method d:(Lsw;)V
       125: aload_1
       126: fconst_1
       127: fconst_1
       128: fconst_1
       129: fconst_1
       130: invokevirtual #1089               // Method eox.a:(FFFF)V
       133: iload         4
       135: ifeq          224
       138: iload         8
       140: ifeq          224
       143: iload         9
       145: ifeq          152
       148: iconst_0
       149: goto          191
       152: fconst_0
       153: bipush        10
       155: aload_0
       156: getfield      #646                // Field aR:I
       159: iadd
       160: i2f
       161: ldc_w         #1188               // float 0.57f
       164: fmul
       165: invokestatic  #1193               // Method apa.a:(F)F
       168: aload_0
       169: getfield      #646                // Field aR:I
       172: i2f
       173: ldc_w         #1194               // float 0.35f
       176: fmul
       177: invokestatic  #1196               // Method apa.b:(F)F
       180: invokestatic  #1202               // Method java/lang/Math.max:(FF)F
       183: invokestatic  #1202               // Method java/lang/Math.max:(FF)F
       186: ldc_w         #1203               // float -6.0f
       189: fmul
       190: f2i
       191: istore        12
       193: aload_1
       194: getstatic     #1205               // Field I:Lacq;
       197: iload         5
       199: bipush        10
       201: iadd
       202: iload         6
       204: iconst_2
       205: iadd
       206: iload         12
       208: iadd
       209: ldc_w         #1206               // float 40.0f
       212: fconst_0
       213: bipush        8
       215: bipush        8
       217: bipush        48
       219: bipush        16
       221: invokevirtual #1030               // Method eox.a:(Lacq;IIFFIIII)V
       224: return

  private void c(eox);
    Code:
         0: ldc_w         #1213               // String LOCAL!
         3: astore_2
         4: aload_1
         5: invokevirtual #1037               // Method eox.c:()Leij;
         8: invokevirtual #1040               // Method eij.a:()V
        11: aload_1
        12: invokevirtual #1037               // Method eox.c:()Leij;
        15: aload_0
        16: getfield      #475                // Field g:I
        19: iconst_2
        20: idiv
        21: bipush        25
        23: isub
        24: i2f
        25: ldc_w         #1183               // float 20.0f
        28: fconst_0
        29: invokevirtual #1044               // Method eij.a:(FFF)V
        32: aload_1
        33: invokevirtual #1037               // Method eox.c:()Leij;
        36: getstatic     #1217               // Field a.f:La;
        39: ldc_w         #1218               // float -20.0f
        42: invokeinterface #1222,  2         // InterfaceMethod a.rotationDegrees:(F)Lorg/joml/Quaternionf;
        47: invokevirtual #1225               // Method eij.a:(Lorg/joml/Quaternionf;)V
        50: aload_1
        51: invokevirtual #1037               // Method eox.c:()Leij;
        54: ldc_w         #1226               // float 1.5f
        57: ldc_w         #1226               // float 1.5f
        60: ldc_w         #1226               // float 1.5f
        63: invokevirtual #1228               // Method eij.b:(FFF)V
        66: aload_1
        67: aload_0
        68: getfield      #409                // Field i:Leov;
        71: ldc_w         #1213               // String LOCAL!
        74: iconst_0
        75: iconst_0
        76: ldc_w         #1229               // int 8388479
        79: iconst_0
        80: invokevirtual #1232               // Method eox.a:(Leov;Ljava/lang/String;IIIZ)I
        83: pop
        84: aload_1
        85: invokevirtual #1037               // Method eox.c:()Leij;
        88: invokevirtual #1047               // Method eij.b:()V
        91: return

  private void d(eox);
    Code:
         0: ldc_w         #1234               // String STAGE!
         3: astore_2
         4: aload_1
         5: invokevirtual #1037               // Method eox.c:()Leij;
         8: invokevirtual #1040               // Method eij.a:()V
        11: aload_1
        12: invokevirtual #1037               // Method eox.c:()Leij;
        15: aload_0
        16: getfield      #475                // Field g:I
        19: iconst_2
        20: idiv
        21: bipush        25
        23: isub
        24: i2f
        25: ldc_w         #1183               // float 20.0f
        28: fconst_0
        29: invokevirtual #1044               // Method eij.a:(FFF)V
        32: aload_1
        33: invokevirtual #1037               // Method eox.c:()Leij;
        36: getstatic     #1217               // Field a.f:La;
        39: ldc_w         #1218               // float -20.0f
        42: invokeinterface #1222,  2         // InterfaceMethod a.rotationDegrees:(F)Lorg/joml/Quaternionf;
        47: invokevirtual #1225               // Method eij.a:(Lorg/joml/Quaternionf;)V
        50: aload_1
        51: invokevirtual #1037               // Method eox.c:()Leij;
        54: ldc_w         #1226               // float 1.5f
        57: ldc_w         #1226               // float 1.5f
        60: ldc_w         #1226               // float 1.5f
        63: invokevirtual #1228               // Method eij.b:(FFF)V
        66: aload_1
        67: aload_0
        68: getfield      #409                // Field i:Leov;
        71: ldc_w         #1234               // String STAGE!
        74: iconst_0
        75: iconst_0
        76: sipush        -256
        79: iconst_0
        80: invokevirtual #1232               // Method eox.a:(Leov;Ljava/lang/String;IIIZ)I
        83: pop
        84: aload_1
        85: invokevirtual #1037               // Method eox.c:()Leij;
        88: invokevirtual #1047               // Method eij.b:()V
        91: return

  public eiu h();
    Code:
         0: new           #2                  // class eiu
         3: dup
         4: aload_0
         5: getfield      #258                // Field aH:Leuq;
         8: invokespecial #1237               // Method "<init>":(Leuq;)V
        11: astore_1
        12: aload_1
        13: aload_0
        14: getfield      #302                // Field f:Lenn;
        17: aload_0
        18: getfield      #475                // Field g:I
        21: aload_0
        22: getfield      #595                // Field h:I
        25: invokevirtual #1240               // Method b:(Lenn;II)V
        28: aload_1
        29: areturn

  public static void a(akx);
    Code:
         0: aload_0
         1: ldc_w         #1243               // String textures/gui/images
         4: invokedynamic #1251,  0           // InvokeDynamic #30:test:()Ljava/util/function/Predicate;
         9: invokeinterface #1256,  3         // InterfaceMethod akx.b:(Ljava/lang/String;Ljava/util/function/Predicate;)Ljava/util/Map;
        14: invokeinterface #1262,  1         // InterfaceMethod java/util/Map.keySet:()Ljava/util/Set;
        19: astore_1
        20: aload_1
        21: invokeinterface #1268,  1         // InterfaceMethod java/util/Collection.stream:()Ljava/util/stream/Stream;
        26: invokedynamic #1272,  0           // InvokeDynamic #31:test:()Ljava/util/function/Predicate;
        31: invokeinterface #1278,  2         // InterfaceMethod java/util/stream/Stream.filter:(Ljava/util/function/Predicate;)Ljava/util/stream/Stream;
        36: invokeinterface #1281,  1         // InterfaceMethod java/util/stream/Stream.toList:()Ljava/util/List;
        41: putstatic     #1103               // Field au:Ljava/util/List;
        44: return

  private static boolean a(acq);
    Code:
         0: aload_0
         1: invokevirtual #1285               // Method acq.b:()Ljava/lang/String;
         4: ldc_w         #1287               // String realms
         7: invokevirtual #318                // Method java/lang/String.equals:(Ljava/lang/Object;)Z
        10: ireturn

  private static boolean b(acq);
    Code:
         0: aload_0
         1: invokevirtual #1289               // Method acq.a:()Ljava/lang/String;
         4: ldc_w         #1291               // String .png
         7: invokevirtual #1295               // Method java/lang/String.endsWith:(Ljava/lang/String;)Z
        10: ireturn

  private static void a(char, eit);
    Code:
         0: aload_1
         1: iload_0
         2: invokevirtual #1298               // Method eit.a:(C)Z
         5: pop
         6: return

  private void a(java.util.UUID, java.lang.Object);
    Code:
         0: aload_0
         1: getfield      #256                // Field bh:Ljava/util/List;
         4: aload_1
         5: invokedynamic #1308,  0           // InvokeDynamic #32:test:(Ljava/util/UUID;)Ljava/util/function/Predicate;
        10: invokeinterface #978,  2          // InterfaceMethod java/util/List.removeIf:(Ljava/util/function/Predicate;)Z
        15: pop
        16: aload_0
        17: invokevirtual #1310               // Method E:()V
        20: return

  private static boolean a(java.util.UUID, ejp);
    Code:
         0: aload_1
         1: invokevirtual #1313               // Method ejp.b:()Z
         4: ifeq          22
         7: aload_0
         8: aload_1
         9: invokevirtual #781                // Method ejp.c:()Ljava/util/UUID;
        12: invokevirtual #1316               // Method java/util/UUID.equals:(Ljava/lang/Object;)Z
        15: ifeq          22
        18: iconst_1
        19: goto          23
        22: iconst_0
        23: ireturn

  private static java.lang.Object a(java.util.UUID, eiz) throws ekm;
    Code:
         0: aload_1
         1: aload_0
         2: invokestatic  #1321               // InterfaceMethod java/util/List.of:(Ljava/lang/Object;)Ljava/util/List;
         5: invokevirtual #1323               // Method eiz.b:(Ljava/util/List;)V
         8: aconst_null
         9: areturn

  private static boolean a(ejq, eiu$d);
    Code:
         0: aload_1
         1: invokevirtual #951                // Method eiu$d.b:()Lejq;
         4: astore_2
         5: aload_2
         6: ifnull        25
         9: aload_2
        10: getfield      #817                // Field ejq.a:J
        13: aload_0
        14: getfield      #817                // Field ejq.a:J
        17: lcmp
        18: ifne          25
        21: iconst_1
        22: goto          26
        25: iconst_0
        26: ireturn

  private void a(ejq, boolean);
    Code:
         0: aload_0
         1: iload_2
         2: aload_1
         3: invokevirtual #1326               // Method a:(ZLejq;)V
         6: return

  private void S();
    Code:
         0: invokestatic  #1332               // Method eiy.a:()Ljava/util/List;
         3: astore_1
         4: invokestatic  #1335               // Method eiz.a:()Leiz;
         7: astore_2
         8: new           #1337               // class ejl
        11: dup
        12: invokespecial #1338               // Method ejl."<init>":()V
        15: astore_3
        16: aload_3
        17: aload_1
        18: putfield      #1340               // Field ejl.a:Ljava/util/List;
        21: aload_3
        22: aload_0
        23: invokevirtual #1342               // Method H:()Ljava/util/List;
        26: putfield      #1344               // Field ejl.b:Ljava/util/List;
        29: aload_2
        30: aload_3
        31: invokevirtual #1347               // Method eiz.a:(Lejl;)V
        34: goto          52
        37: astore        4
        39: getstatic     #1349               // Field a:Lorg/slf4j/Logger;
        42: ldc_w         #1351               // String Could not send ping result to Realms:
        45: aload         4
        47: invokeinterface #1357,  3         // InterfaceMethod org/slf4j/Logger.warn:(Ljava/lang/String;Ljava/lang/Throwable;)V
        52: return
      Exception table:
         from    to  target type
            29    34    37   Class java/lang/Throwable

  private void a(java.util.List, java.lang.Object);
    Code:
         0: aload_0
         1: getfield      #232                // Field ax:Ljava/util/Set;
         4: aload_1
         5: invokeinterface #1364,  2         // InterfaceMethod java/util/Set.addAll:(Ljava/util/Collection;)Z
        10: pop
        11: return

  private static java.lang.Object a(java.util.List, eiz) throws ekm;
    Code:
         0: aload_1
         1: aload_0
         2: invokevirtual #1366               // Method eiz.a:(Ljava/util/List;)V
         5: aconst_null
         6: areturn

  private static java.lang.Void a(java.lang.Throwable);
    Code:
         0: getstatic     #1349               // Field a:Lorg/slf4j/Logger;
         3: ldc_w         #1368               // String Failed to execute call to Realms Service
         6: aload_0
         7: invokeinterface #1371,  3         // InterfaceMethod org/slf4j/Logger.error:(Ljava/lang/String;Ljava/lang/Throwable;)V
        12: aconst_null
        13: areturn

  private static java.lang.Object a(eiu$i, enn);
    Code:
         0: aload_0
         1: aload_1
         2: invokestatic  #1374               // Method eiz.a:(Lenn;)Leiz;
         5: invokeinterface #1376,  2         // InterfaceMethod eiu$i.request:(Leiz;)Ljava/lang/Object;
        10: areturn
        11: astore_2
        12: new           #1378               // class java/lang/RuntimeException
        15: dup
        16: aload_2
        17: invokespecial #1381               // Method java/lang/RuntimeException."<init>":(Ljava/lang/Throwable;)V
        20: athrow
      Exception table:
         from    to  target type
             0    10    11   Class ekm

  private void a(ekq, ejo);
    Code:
         0: aload_1
         1: getfield      #422                // Field ekq.h:Lekr;
         4: aload_2
         5: invokevirtual #1384               // Method ekr.a:(Lejo;)V
         8: aload_0
         9: aload_1
        10: getfield      #422                // Field ekq.h:Lekr;
        13: invokevirtual #426                // Method ekr.a:()Z
        16: putfield      #428                // Field aY:Z
        19: aload_0
        20: aload_1
        21: getfield      #422                // Field ekq.h:Lekr;
        24: invokevirtual #429                // Method ekr.b:()Ljava/lang/String;
        27: putfield      #431                // Field aZ:Ljava/lang/String;
        30: aload_0
        31: aconst_null
        32: invokevirtual #406                // Method a:(Lejq;)V
        35: return

  private void a(ejv);
    Code:
         0: aload_1
         1: getfield      #1388               // Field ejv.a:Ljava/util/List;
         4: invokeinterface #288,  1          // InterfaceMethod java/util/List.iterator:()Ljava/util/Iterator;
         9: astore_2
        10: aload_2
        11: invokeinterface #293,  1          // InterfaceMethod java/util/Iterator.hasNext:()Z
        16: ifeq          90
        19: aload_2
        20: invokeinterface #297,  1          // InterfaceMethod java/util/Iterator.next:()Ljava/lang/Object;
        25: checkcast     #1390               // class eju
        28: astore_3
        29: aload_0
        30: getfield      #240                // Field aP:Ljava/util/List;
        33: invokeinterface #288,  1          // InterfaceMethod java/util/List.iterator:()Ljava/util/Iterator;
        38: astore        4
        40: aload         4
        42: invokeinterface #293,  1          // InterfaceMethod java/util/Iterator.hasNext:()Z
        47: ifeq          87
        50: aload         4
        52: invokeinterface #297,  1          // InterfaceMethod java/util/Iterator.next:()Ljava/lang/Object;
        57: checkcast     #65                 // class ejq
        60: astore        5
        62: aload         5
        64: getfield      #817                // Field ejq.a:J
        67: aload_3
        68: getfield      #1391               // Field eju.a:J
        71: lcmp
        72: ifne          84
        75: aload         5
        77: aload_3
        78: invokevirtual #1394               // Method ejq.a:(Leju;)V
        81: goto          87
        84: goto          40
        87: goto          10
        90: return

  private void a(java.lang.Boolean);
    Code:
         0: aload_0
         1: getfield      #282                // Field aW:Z
         4: ifeq          8
         7: return
         8: aload_1
         9: invokevirtual #1401               // Method java/lang/Boolean.booleanValue:()Z
        12: aload_0
        13: getfield      #280                // Field aV:Z
        16: if_icmpeq     42
        19: aload_0
        20: invokevirtual #615                // Method a:()Z
        23: ifeq          42
        26: aload_0
        27: aload_1
        28: invokevirtual #1401               // Method java/lang/Boolean.booleanValue:()Z
        31: putfield      #280                // Field aV:Z
        34: aload_0
        35: iconst_0
        36: putfield      #379                // Field aX:Z
        39: goto          50
        42: aload_0
        43: aload_1
        44: invokevirtual #1401               // Method java/lang/Boolean.booleanValue:()Z
        47: putfield      #280                // Field aV:Z
        50: return

  private void a(java.lang.Integer);
    Code:
         0: aload_0
         1: aload_1
         2: invokevirtual #1405               // Method java/lang/Integer.intValue:()I
         5: putfield      #1407               // Field aQ:I
         8: aload_0
         9: getfield      #1407               // Field aQ:I
        12: ifle          56
        15: aload_0
        16: getfield      #268                // Field aF:Lcom/google/common/util/concurrent/RateLimiter;
        19: iconst_1
        20: invokevirtual #1411               // Method com/google/common/util/concurrent/RateLimiter.tryAcquire:(I)Z
        23: ifeq          56
        26: aload_0
        27: getfield      #302                // Field f:Lenn;
        30: invokevirtual #1083               // Method enn.aU:()Lenf;
        33: ldc_w         #1413               // String mco.configure.world.invite.narration
        36: iconst_1
        37: anewarray     #1164               // class java/lang/Object
        40: dup
        41: iconst_0
        42: aload_0
        43: getfield      #1407               // Field aQ:I
        46: invokestatic  #1169               // Method java/lang/Integer.valueOf:(I)Ljava/lang/Integer;
        49: aastore
        50: invokestatic  #1172               // InterfaceMethod sw.a:(Ljava/lang/String;[Ljava/lang/Object;)Ltj;
        53: invokevirtual #1085               // Method enf.c:(Lsw;)V
        56: return

  private void c(java.util.List);
    Code:
         0: aload_0
         1: getfield      #256                // Field bh:Ljava/util/List;
         4: invokeinterface #1417,  1         // InterfaceMethod java/util/List.clear:()V
         9: aload_0
        10: getfield      #256                // Field bh:Ljava/util/List;
        13: aload_1
        14: invokeinterface #1418,  2         // InterfaceMethod java/util/List.addAll:(Ljava/util/Collection;)Z
        19: pop
        20: aload_0
        21: invokevirtual #1310               // Method E:()V
        24: return

  private void d(java.util.List);
    Code:
         0: aload_0
         1: getfield      #433                // Field aw:Leks;
         4: aload_1
         5: invokevirtual #1421               // Method eks.a:(Ljava/util/List;)Ljava/util/List;
         8: astore_2
         9: iconst_0
        10: istore_3
        11: aload_2
        12: invokeinterface #288,  1          // InterfaceMethod java/util/List.iterator:()Ljava/util/Iterator;
        17: astore        4
        19: aload         4
        21: invokeinterface #293,  1          // InterfaceMethod java/util/Iterator.hasNext:()Z
        26: ifeq          55
        29: aload         4
        31: invokeinterface #297,  1          // InterfaceMethod java/util/Iterator.next:()Ljava/lang/Object;
        36: checkcast     #65                 // class ejq
        39: astore        5
        41: aload_0
        42: aload         5
        44: invokevirtual #860                // Method k:(Lejq;)Z
        47: ifeq          52
        50: iconst_1
        51: istore_3
        52: goto          19
        55: aload_0
        56: aload_2
        57: putfield      #240                // Field aP:Ljava/util/List;
        60: aload_0
        61: iconst_1
        62: putfield      #278                // Field aS:Z
        65: aload_0
        66: invokevirtual #1310               // Method E:()V
        69: getstatic     #1423               // Field aE:Z
        72: ifne          87
        75: iload_3
        76: ifeq          87
        79: iconst_1
        80: putstatic     #1423               // Field aE:Z
        83: aload_0
        84: invokevirtual #1425               // Method G:()V
        87: return

  private static void a(eiu, eqt);
    Code:
         0: aload_0
         1: aload_1
         2: invokevirtual #449                // Method d:(Leqt;)Leqt;
         5: checkcast     #611                // class epf
         8: pop
         9: return

  private void a(epi);
    Code:
         0: aload_0
         1: getfield      #644                // Field aU:Z
         4: ifne          18
         7: aload_0
         8: getfield      #302                // Field f:Lenn;
        11: aload_0
        12: getfield      #258                // Field aH:Leuq;
        15: invokevirtual #366                // Method enn.a:(Leuq;)V
        18: return

  private void b(epi);
    Code:
         0: aload_0
         1: aload_0
         2: invokevirtual #812                // Method O:()Lejq;
         5: invokevirtual #1428               // Method h:(Lejq;)V
         8: return

  private void c(epi);
    Code:
         0: aload_0
         1: aload_0
         2: invokevirtual #812                // Method O:()Lejq;
         5: invokevirtual #1430               // Method f:(Lejq;)V
         8: return

  private void d(epi);
    Code:
         0: aload_0
         1: aload_0
         2: invokevirtual #812                // Method O:()Lejq;
         5: invokevirtual #1432               // Method g:(Lejq;)V
         8: return

  private void e(epi);
    Code:
         0: aload_0
         1: aload_0
         2: invokevirtual #812                // Method O:()Lejq;
         5: aload_0
         6: invokevirtual #1434               // Method a:(Lejq;Leuq;)V
         9: return

  private static void f(epi);
    Code:
         0: invokestatic  #888                // Method ac.i:()Lac$b;
         3: ldc_w         #1436               // String https://aka.ms/BuyJavaRealms
         6: invokevirtual #889                // Method ac$b.a:(Ljava/lang/String;)V
         9: return

  private void g(epi);
    Code:
         0: aload_0
         1: getfield      #280                // Field aV:Z
         4: ifeq          14
         7: aload_0
         8: getfield      #282                // Field aW:Z
        11: ifeq          15
        14: return
        15: invokestatic  #888                // Method ac.i:()Lac$b;
        18: ldc_w         #1438               // String https://aka.ms/startjavarealmstrial
        21: invokevirtual #889                // Method ac$b.a:(Ljava/lang/String;)V
        24: aload_0
        25: getfield      #302                // Field f:Lenn;
        28: aload_0
        29: getfield      #258                // Field aH:Leuq;
        32: invokevirtual #366                // Method enn.a:(Leuq;)V
        35: return

  private void h(epi);
    Code:
         0: aload_0
         1: aload_0
         2: getfield      #321                // Field aT:Z
         5: ifne          12
         8: iconst_1
         9: goto          13
        12: iconst_0
        13: putfield      #321                // Field aT:Z
        16: return

  private void T();
    Code:
         0: getstatic     #900                // Field eiz.a:Leiz$b;
         3: getstatic     #908                // Field eiz$b.c:Leiz$b;
         6: if_acmpne     16
         9: aload_0
        10: invokevirtual #1440               // Method M:()V
        13: goto          20
        16: aload_0
        17: invokevirtual #1442               // Method L:()V
        20: return

  private void U();
    Code:
         0: getstatic     #900                // Field eiz.a:Leiz$b;
         3: getstatic     #902                // Field eiz$b.b:Leiz$b;
         6: if_acmpne     16
         9: aload_0
        10: invokevirtual #1440               // Method M:()V
        13: goto          20
        16: aload_0
        17: invokevirtual #1444               // Method K:()V
        20: return

  private static void V();
    Code:
         0: getstatic     #917                // Field ay:Z
         3: ifne          10
         6: iconst_1
         7: goto          11
        10: iconst_0
        11: putstatic     #917                // Field ay:Z
        14: return

  static enn a(eiu);
    Code:
         0: aload_0
         1: getfield      #302                // Field f:Lenn;
         4: areturn

  static enn b(eiu);
    Code:
         0: aload_0
         1: getfield      #302                // Field f:Lenn;
         4: areturn

  static enn c(eiu);
    Code:
         0: aload_0
         1: getfield      #302                // Field f:Lenn;
         4: areturn

  static enn d(eiu);
    Code:
         0: aload_0
         1: getfield      #302                // Field f:Lenn;
         4: areturn

  static enn e(eiu);
    Code:
         0: aload_0
         1: getfield      #302                // Field f:Lenn;
         4: areturn

  static enn f(eiu);
    Code:
         0: aload_0
         1: getfield      #302                // Field f:Lenn;
         4: areturn

  static enn g(eiu);
    Code:
         0: aload_0
         1: getfield      #302                // Field f:Lenn;
         4: areturn

  static enn h(eiu);
    Code:
         0: aload_0
         1: getfield      #302                // Field f:Lenn;
         4: areturn

  static enn i(eiu);
    Code:
         0: aload_0
         1: getfield      #302                // Field f:Lenn;
         4: areturn

  static enn j(eiu);
    Code:
         0: aload_0
         1: getfield      #302                // Field f:Lenn;
         4: areturn

  static enn k(eiu);
    Code:
         0: aload_0
         1: getfield      #302                // Field f:Lenn;
         4: areturn

  static enn l(eiu);
    Code:
         0: aload_0
         1: getfield      #302                // Field f:Lenn;
         4: areturn

  static enn m(eiu);
    Code:
         0: aload_0
         1: getfield      #302                // Field f:Lenn;
         4: areturn

  static eov n(eiu);
    Code:
         0: aload_0
         1: getfield      #409                // Field i:Leov;
         4: areturn

  static eov o(eiu);
    Code:
         0: aload_0
         1: getfield      #409                // Field i:Leov;
         4: areturn

  static eov p(eiu);
    Code:
         0: aload_0
         1: getfield      #409                // Field i:Leov;
         4: areturn

  static enn q(eiu);
    Code:
         0: aload_0
         1: getfield      #302                // Field f:Lenn;
         4: areturn

  static enn r(eiu);
    Code:
         0: aload_0
         1: getfield      #302                // Field f:Lenn;
         4: areturn

  static enn s(eiu);
    Code:
         0: aload_0
         1: getfield      #302                // Field f:Lenn;
         4: areturn

  static eov t(eiu);
    Code:
         0: aload_0
         1: getfield      #409                // Field i:Leov;
         4: areturn

  static eov u(eiu);
    Code:
         0: aload_0
         1: getfield      #409                // Field i:Leov;
         4: areturn

  static eov v(eiu);
    Code:
         0: aload_0
         1: getfield      #409                // Field i:Leov;
         4: areturn

  static eov w(eiu);
    Code:
         0: aload_0
         1: getfield      #409                // Field i:Leov;
         4: areturn

  static void a(eiu, sw);
    Code:
         0: aload_0
         1: aload_1
         2: invokevirtual #1152               // Method d:(Lsw;)V
         5: return

  static eov x(eiu);
    Code:
         0: aload_0
         1: getfield      #409                // Field i:Leov;
         4: areturn

  static eov y(eiu);
    Code:
         0: aload_0
         1: getfield      #409                // Field i:Leov;
         4: areturn

  static eov z(eiu);
    Code:
         0: aload_0
         1: getfield      #409                // Field i:Leov;
         4: areturn

  static eov A(eiu);
    Code:
         0: aload_0
         1: getfield      #409                // Field i:Leov;
         4: areturn

  static eov B(eiu);
    Code:
         0: aload_0
         1: getfield      #409                // Field i:Leov;
         4: areturn

  static eov C(eiu);
    Code:
         0: aload_0
         1: getfield      #409                // Field i:Leov;
         4: areturn

  static eov D(eiu);
    Code:
         0: aload_0
         1: getfield      #409                // Field i:Leov;
         4: areturn

  static enn E(eiu);
    Code:
         0: aload_0
         1: getfield      #302                // Field f:Lenn;
         4: areturn

  static {};
    Code:
         0: invokestatic  #1464               // Method com/mojang/logging/LogUtils.getLogger:()Lorg/slf4j/Logger;
         3: putstatic     #1349               // Field a:Lorg/slf4j/Logger;
         6: new           #1108               // class acq
         9: dup
        10: ldc_w         #1287               // String realms
        13: ldc_w         #1466               // String textures/gui/realms/on_icon.png
        16: invokespecial #1469               // Method acq."<init>":(Ljava/lang/String;Ljava/lang/String;)V
        19: putstatic     #1174               // Field b:Lacq;
        22: new           #1108               // class acq
        25: dup
        26: ldc_w         #1287               // String realms
        29: ldc_w         #1471               // String textures/gui/realms/off_icon.png
        32: invokespecial #1469               // Method acq."<init>":(Ljava/lang/String;Ljava/lang/String;)V
        35: putstatic     #1178               // Field c:Lacq;
        38: new           #1108               // class acq
        41: dup
        42: ldc_w         #1287               // String realms
        45: ldc_w         #1473               // String textures/gui/realms/expired_icon.png
        48: invokespecial #1469               // Method acq."<init>":(Ljava/lang/String;Ljava/lang/String;)V
        51: putstatic     #1148               // Field G:Lacq;
        54: new           #1108               // class acq
        57: dup
        58: ldc_w         #1287               // String realms
        61: ldc_w         #1475               // String textures/gui/realms/expires_soon_icon.png
        64: invokespecial #1469               // Method acq."<init>":(Ljava/lang/String;Ljava/lang/String;)V
        67: putstatic     #1155               // Field H:Lacq;
        70: new           #1108               // class acq
        73: dup
        74: ldc_w         #1287               // String realms
        77: ldc_w         #1477               // String textures/gui/realms/invitation_icons.png
        80: invokespecial #1469               // Method acq."<init>":(Ljava/lang/String;Ljava/lang/String;)V
        83: putstatic     #1205               // Field I:Lacq;
        86: new           #1108               // class acq
        89: dup
        90: ldc_w         #1287               // String realms
        93: ldc_w         #1479               // String textures/gui/realms/invite_icon.png
        96: invokespecial #1469               // Method acq."<init>":(Ljava/lang/String;Ljava/lang/String;)V
        99: putstatic     #1481               // Field J:Lacq;
       102: new           #1108               // class acq
       105: dup
       106: ldc_w         #1287               // String realms
       109: ldc_w         #1483               // String textures/gui/realms/world_icon.png
       112: invokespecial #1469               // Method acq."<init>":(Ljava/lang/String;Ljava/lang/String;)V
       115: putstatic     #1485               // Field K:Lacq;
       118: new           #1108               // class acq
       121: dup
       122: ldc_w         #1287               // String realms
       125: ldc_w         #1487               // String textures/gui/title/realms.png
       128: invokespecial #1469               // Method acq."<init>":(Ljava/lang/String;Ljava/lang/String;)V
       131: putstatic     #1025               // Field L:Lacq;
       134: new           #1108               // class acq
       137: dup
       138: ldc_w         #1287               // String realms
       141: ldc_w         #1489               // String textures/gui/realms/news_icon.png
       144: invokespecial #1469               // Method acq."<init>":(Ljava/lang/String;Ljava/lang/String;)V
       147: putstatic     #1185               // Field M:Lacq;
       150: new           #1108               // class acq
       153: dup
       154: ldc_w         #1287               // String realms
       157: ldc_w         #1491               // String textures/gui/realms/popup.png
       160: invokespecial #1469               // Method acq."<init>":(Ljava/lang/String;Ljava/lang/String;)V
       163: putstatic     #1101               // Field N:Lacq;
       166: new           #1108               // class acq
       169: dup
       170: ldc_w         #1287               // String realms
       173: ldc_w         #1493               // String textures/gui/realms/darken.png
       176: invokespecial #1469               // Method acq."<init>":(Ljava/lang/String;Ljava/lang/String;)V
       179: putstatic     #1096               // Field O:Lacq;
       182: new           #1108               // class acq
       185: dup
       186: ldc_w         #1287               // String realms
       189: ldc_w         #1495               // String textures/gui/realms/cross_icon.png
       192: invokespecial #1469               // Method acq."<init>":(Ljava/lang/String;Ljava/lang/String;)V
       195: putstatic     #1497               // Field P:Lacq;
       198: new           #1108               // class acq
       201: dup
       202: ldc_w         #1287               // String realms
       205: ldc_w         #1499               // String textures/gui/realms/trial_icon.png
       208: invokespecial #1469               // Method acq."<init>":(Ljava/lang/String;Ljava/lang/String;)V
       211: putstatic     #1056               // Field Q:Lacq;
       214: new           #1108               // class acq
       217: dup
       218: ldc_w         #1501               // String minecraft
       221: ldc_w         #1503               // String textures/gui/info_icon.png
       224: invokespecial #1469               // Method acq."<init>":(Ljava/lang/String;Ljava/lang/String;)V
       227: putstatic     #1505               // Field R:Lacq;
       230: ldc_w         #1507               // String mco.trial.message.line1
       233: invokestatic  #461                // InterfaceMethod sw.c:(Ljava/lang/String;)Ltj;
       236: ldc_w         #1509               // String mco.trial.message.line2
       239: invokestatic  #461                // InterfaceMethod sw.c:(Ljava/lang/String;)Ltj;
       242: invokestatic  #1512               // Method com/google/common/collect/ImmutableList.of:(Ljava/lang/Object;Ljava/lang/Object;)Lcom/google/common/collect/ImmutableList;
       245: putstatic     #1514               // Field S:Ljava/util/List;
       248: ldc_w         #1516               // String mco.selectServer.uninitialized
       251: invokestatic  #461                // InterfaceMethod sw.c:(Ljava/lang/String;)Ltj;
       254: putstatic     #1518               // Field T:Lsw;
       257: ldc_w         #1520               // String mco.selectServer.expiredList
       260: invokestatic  #461                // InterfaceMethod sw.c:(Ljava/lang/String;)Ltj;
       263: putstatic     #1522               // Field U:Lsw;
       266: ldc_w         #1524               // String mco.selectServer.expiredRenew
       269: invokestatic  #461                // InterfaceMethod sw.c:(Ljava/lang/String;)Ltj;
       272: putstatic     #528                // Field V:Lsw;
       275: ldc_w         #1526               // String mco.selectServer.expiredTrial
       278: invokestatic  #461                // InterfaceMethod sw.c:(Ljava/lang/String;)Ltj;
       281: putstatic     #1528               // Field W:Lsw;
       284: ldc_w         #1530               // String mco.selectServer.minigame
       287: invokestatic  #461                // InterfaceMethod sw.c:(Ljava/lang/String;)Ltj;
       290: getstatic     #1532               // Field sv.t:Lsw;
       293: invokevirtual #1537               // Method tj.b:(Lsw;)Ltj;
       296: putstatic     #1539               // Field X:Lsw;
       299: ldc_w         #1541               // String mco.selectServer.popup
       302: invokestatic  #461                // InterfaceMethod sw.c:(Ljava/lang/String;)Ltj;
       305: putstatic     #411                // Field Y:Lsw;
       308: ldc_w         #1543               // String mco.selectServer.play
       311: invokestatic  #461                // InterfaceMethod sw.c:(Ljava/lang/String;)Ltj;
       314: putstatic     #509                // Field Z:Lsw;
       317: ldc_w         #1545               // String mco.selectServer.leave
       320: invokestatic  #461                // InterfaceMethod sw.c:(Ljava/lang/String;)Ltj;
       323: putstatic     #536                // Field aa:Lsw;
       326: ldc_w         #1547               // String mco.selectServer.configure
       329: invokestatic  #461                // InterfaceMethod sw.c:(Ljava/lang/String;)Ltj;
       332: putstatic     #520                // Field ab:Lsw;
       335: ldc_w         #1549               // String mco.selectServer.expired
       338: invokestatic  #461                // InterfaceMethod sw.c:(Ljava/lang/String;)Ltj;
       341: putstatic     #1150               // Field ac:Lsw;
       344: ldc_w         #1551               // String mco.selectServer.expires.soon
       347: invokestatic  #461                // InterfaceMethod sw.c:(Ljava/lang/String;)Ltj;
       350: putstatic     #1158               // Field ad:Lsw;
       353: ldc_w         #1553               // String mco.selectServer.expires.day
       356: invokestatic  #461                // InterfaceMethod sw.c:(Ljava/lang/String;)Ltj;
       359: putstatic     #1160               // Field ae:Lsw;
       362: ldc_w         #1555               // String mco.selectServer.open
       365: invokestatic  #461                // InterfaceMethod sw.c:(Ljava/lang/String;)Ltj;
       368: putstatic     #1176               // Field af:Lsw;
       371: ldc_w         #1557               // String mco.selectServer.closed
       374: invokestatic  #461                // InterfaceMethod sw.c:(Ljava/lang/String;)Ltj;
       377: putstatic     #1180               // Field ag:Lsw;
       380: ldc_w         #1559               // String mco.news
       383: invokestatic  #461                // InterfaceMethod sw.c:(Ljava/lang/String;)Ltj;
       386: putstatic     #1187               // Field ah:Lsw;
       389: ldc_w         #1561               // String gui.narrate.button
       392: iconst_1
       393: anewarray     #1164               // class java/lang/Object
       396: dup
       397: iconst_0
       398: getstatic     #1518               // Field T:Lsw;
       401: aastore
       402: invokestatic  #1172               // InterfaceMethod sw.a:(Ljava/lang/String;[Ljava/lang/Object;)Ltj;
       405: putstatic     #1563               // Field ai:Lsw;
       408: getstatic     #1514               // Field S:Ljava/util/List;
       411: invokestatic  #1566               // Method sv.a:(Ljava/util/Collection;)Lsw;
       414: putstatic     #1568               // Field aj:Lsw;
       417: invokestatic  #238                // Method com/google/common/collect/ImmutableList.of:()Lcom/google/common/collect/ImmutableList;
       420: putstatic     #1103               // Field au:Ljava/util/List;
       423: iconst_m1
       424: putstatic     #386                // Field az:I
       427: return
}
